{
  "status": "done",
  "assets": {
    "css/add_forge_now.4f93c9769bc36a247915.css": {
      "name": "css/add_forge_now.4f93c9769bc36a247915.css",
      "path": "/var/lib/jenkins/agent-workdir/workspace/DWAPPS/pypi-upload/static/css/add_forge_now.4f93c9769bc36a247915.css",
      "publicPath": "/static/css/add_forge_now.4f93c9769bc36a247915.css"
    },
    "css/add_forge_now.4f93c9769bc36a247915.css.map": {
      "name": "css/add_forge_now.4f93c9769bc36a247915.css.map",
      "path": "/var/lib/jenkins/agent-workdir/workspace/DWAPPS/pypi-upload/static/css/add_forge_now.4f93c9769bc36a247915.css.map",
      "publicPath": "/static/css/add_forge_now.4f93c9769bc36a247915.css.map"
    },
    "css/archive_coverage.6573148e19d3c98015b4.css": {
      "name": "css/archive_coverage.6573148e19d3c98015b4.css",
      "path": "/var/lib/jenkins/agent-workdir/workspace/DWAPPS/pypi-upload/static/css/archive_coverage.6573148e19d3c98015b4.css",
      "publicPath": "/static/css/archive_coverage.6573148e19d3c98015b4.css"
    },
    "css/archive_coverage.6573148e19d3c98015b4.css.map": {
      "name": "css/archive_coverage.6573148e19d3c98015b4.css.map",
      "path": "/var/lib/jenkins/agent-workdir/workspace/DWAPPS/pypi-upload/static/css/archive_coverage.6573148e19d3c98015b4.css.map",
      "publicPath": "/static/css/archive_coverage.6573148e19d3c98015b4.css.map"
    },
    "css/auth.0336a94c2c02b4b2a4f4.css": {
      "name": "css/auth.0336a94c2c02b4b2a4f4.css",
      "path": "/var/lib/jenkins/agent-workdir/workspace/DWAPPS/pypi-upload/static/css/auth.0336a94c2c02b4b2a4f4.css",
      "publicPath": "/static/css/auth.0336a94c2c02b4b2a4f4.css"
    },
    "css/auth.0336a94c2c02b4b2a4f4.css.map": {
      "name": "css/auth.0336a94c2c02b4b2a4f4.css.map",
      "path": "/var/lib/jenkins/agent-workdir/workspace/DWAPPS/pypi-upload/static/css/auth.0336a94c2c02b4b2a4f4.css.map",
      "publicPath": "/static/css/auth.0336a94c2c02b4b2a4f4.css.map"
    },
    "css/badges.03c8b295a163a9306210.css": {
      "name": "css/badges.03c8b295a163a9306210.css",
      "path": "/var/lib/jenkins/agent-workdir/workspace/DWAPPS/pypi-upload/static/css/badges.03c8b295a163a9306210.css",
      "publicPath": "/static/css/badges.03c8b295a163a9306210.css"
    },
    "css/badges.03c8b295a163a9306210.css.map": {
      "name": "css/badges.03c8b295a163a9306210.css.map",
      "path": "/var/lib/jenkins/agent-workdir/workspace/DWAPPS/pypi-upload/static/css/badges.03c8b295a163a9306210.css.map",
      "publicPath": "/static/css/badges.03c8b295a163a9306210.css.map"
    },
    "css/browse.f5afe9b68b860a92d393.css": {
      "name": "css/browse.f5afe9b68b860a92d393.css",
      "path": "/var/lib/jenkins/agent-workdir/workspace/DWAPPS/pypi-upload/static/css/browse.f5afe9b68b860a92d393.css",
      "publicPath": "/static/css/browse.f5afe9b68b860a92d393.css"
    },
    "css/browse.f5afe9b68b860a92d393.css.map": {
      "name": "css/browse.f5afe9b68b860a92d393.css.map",
      "path": "/var/lib/jenkins/agent-workdir/workspace/DWAPPS/pypi-upload/static/css/browse.f5afe9b68b860a92d393.css.map",
      "publicPath": "/static/css/browse.f5afe9b68b860a92d393.css.map"
    },
    "css/guided_tour.1bfa315c78e66451b0b2.css": {
      "name": "css/guided_tour.1bfa315c78e66451b0b2.css",
      "path": "/var/lib/jenkins/agent-workdir/workspace/DWAPPS/pypi-upload/static/css/guided_tour.1bfa315c78e66451b0b2.css",
      "publicPath": "/static/css/guided_tour.1bfa315c78e66451b0b2.css"
    },
    "css/guided_tour.1bfa315c78e66451b0b2.css.map": {
      "name": "css/guided_tour.1bfa315c78e66451b0b2.css.map",
      "path": "/var/lib/jenkins/agent-workdir/workspace/DWAPPS/pypi-upload/static/css/guided_tour.1bfa315c78e66451b0b2.css.map",
      "publicPath": "/static/css/guided_tour.1bfa315c78e66451b0b2.css.map"
    },
    "css/highlightjs.647c2546fa20fb2773b1.css": {
      "name": "css/highlightjs.647c2546fa20fb2773b1.css",
      "path": "/var/lib/jenkins/agent-workdir/workspace/DWAPPS/pypi-upload/static/css/highlightjs.647c2546fa20fb2773b1.css",
      "publicPath": "/static/css/highlightjs.647c2546fa20fb2773b1.css"
    },
    "css/highlightjs.647c2546fa20fb2773b1.css.map": {
      "name": "css/highlightjs.647c2546fa20fb2773b1.css.map",
      "path": "/var/lib/jenkins/agent-workdir/workspace/DWAPPS/pypi-upload/static/css/highlightjs.647c2546fa20fb2773b1.css.map",
      "publicPath": "/static/css/highlightjs.647c2546fa20fb2773b1.css.map"
    },
    "css/org.fdb2f5350b5554094ca4.css": {
      "name": "css/org.fdb2f5350b5554094ca4.css",
      "path": "/var/lib/jenkins/agent-workdir/workspace/DWAPPS/pypi-upload/static/css/org.fdb2f5350b5554094ca4.css",
      "publicPath": "/static/css/org.fdb2f5350b5554094ca4.css"
    },
    "css/org.fdb2f5350b5554094ca4.css.map": {
      "name": "css/org.fdb2f5350b5554094ca4.css.map",
      "path": "/var/lib/jenkins/agent-workdir/workspace/DWAPPS/pypi-upload/static/css/org.fdb2f5350b5554094ca4.css.map",
      "publicPath": "/static/css/org.fdb2f5350b5554094ca4.css.map"
    },
    "css/origin_visits.405bdab2e61c346d77f1.css": {
      "name": "css/origin_visits.405bdab2e61c346d77f1.css",
      "path": "/var/lib/jenkins/agent-workdir/workspace/DWAPPS/pypi-upload/static/css/origin_visits.405bdab2e61c346d77f1.css",
      "publicPath": "/static/css/origin_visits.405bdab2e61c346d77f1.css"
    },
    "css/origin_visits.405bdab2e61c346d77f1.css.map": {
      "name": "css/origin_visits.405bdab2e61c346d77f1.css.map",
      "path": "/var/lib/jenkins/agent-workdir/workspace/DWAPPS/pypi-upload/static/css/origin_visits.405bdab2e61c346d77f1.css.map",
      "publicPath": "/static/css/origin_visits.405bdab2e61c346d77f1.css.map"
    },
    "css/revision.4f3cb8316771ce5cd8b1.css": {
      "name": "css/revision.4f3cb8316771ce5cd8b1.css",
      "path": "/var/lib/jenkins/agent-workdir/workspace/DWAPPS/pypi-upload/static/css/revision.4f3cb8316771ce5cd8b1.css",
      "publicPath": "/static/css/revision.4f3cb8316771ce5cd8b1.css"
    },
    "css/revision.4f3cb8316771ce5cd8b1.css.map": {
      "name": "css/revision.4f3cb8316771ce5cd8b1.css.map",
      "path": "/var/lib/jenkins/agent-workdir/workspace/DWAPPS/pypi-upload/static/css/revision.4f3cb8316771ce5cd8b1.css.map",
      "publicPath": "/static/css/revision.4f3cb8316771ce5cd8b1.css.map"
    },
    "css/showdown.426fbf6a7a6653fd4cbb.css": {
      "name": "css/showdown.426fbf6a7a6653fd4cbb.css",
      "path": "/var/lib/jenkins/agent-workdir/workspace/DWAPPS/pypi-upload/static/css/showdown.426fbf6a7a6653fd4cbb.css",
      "publicPath": "/static/css/showdown.426fbf6a7a6653fd4cbb.css"
    },
    "css/showdown.426fbf6a7a6653fd4cbb.css.map": {
      "name": "css/showdown.426fbf6a7a6653fd4cbb.css.map",
      "path": "/var/lib/jenkins/agent-workdir/workspace/DWAPPS/pypi-upload/static/css/showdown.426fbf6a7a6653fd4cbb.css.map",
      "publicPath": "/static/css/showdown.426fbf6a7a6653fd4cbb.css.map"
    },
    "css/vault.25fc5883f848b48ffa5b.css": {
      "name": "css/vault.25fc5883f848b48ffa5b.css",
      "path": "/var/lib/jenkins/agent-workdir/workspace/DWAPPS/pypi-upload/static/css/vault.25fc5883f848b48ffa5b.css",
      "publicPath": "/static/css/vault.25fc5883f848b48ffa5b.css"
    },
    "css/vault.25fc5883f848b48ffa5b.css.map": {
      "name": "css/vault.25fc5883f848b48ffa5b.css.map",
      "path": "/var/lib/jenkins/agent-workdir/workspace/DWAPPS/pypi-upload/static/css/vault.25fc5883f848b48ffa5b.css.map",
      "publicPath": "/static/css/vault.25fc5883f848b48ffa5b.css.map"
    },
    "css/vendors.d0eb81594ae7205efdb0.css": {
      "name": "css/vendors.d0eb81594ae7205efdb0.css",
      "path": "/var/lib/jenkins/agent-workdir/workspace/DWAPPS/pypi-upload/static/css/vendors.d0eb81594ae7205efdb0.css",
      "publicPath": "/static/css/vendors.d0eb81594ae7205efdb0.css"
    },
    "css/vendors.d0eb81594ae7205efdb0.css.map": {
      "name": "css/vendors.d0eb81594ae7205efdb0.css.map",
      "path": "/var/lib/jenkins/agent-workdir/workspace/DWAPPS/pypi-upload/static/css/vendors.d0eb81594ae7205efdb0.css.map",
      "publicPath": "/static/css/vendors.d0eb81594ae7205efdb0.css.map"
    },
    "css/webapp.0041e30b97d702aceb6a.css": {
      "name": "css/webapp.0041e30b97d702aceb6a.css",
      "path": "/var/lib/jenkins/agent-workdir/workspace/DWAPPS/pypi-upload/static/css/webapp.0041e30b97d702aceb6a.css",
      "publicPath": "/static/css/webapp.0041e30b97d702aceb6a.css"
    },
    "css/webapp.0041e30b97d702aceb6a.css.map": {
      "name": "css/webapp.0041e30b97d702aceb6a.css.map",
      "path": "/var/lib/jenkins/agent-workdir/workspace/DWAPPS/pypi-upload/static/css/webapp.0041e30b97d702aceb6a.css.map",
      "publicPath": "/static/css/webapp.0041e30b97d702aceb6a.css.map"
    },
    "fonts/alegreya-latin-400.woff": {
      "name": "fonts/alegreya-latin-400.woff",
      "path": "/var/lib/jenkins/agent-workdir/workspace/DWAPPS/pypi-upload/static/fonts/alegreya-latin-400.woff",
      "publicPath": "/static/fonts/alegreya-latin-400.woff"
    },
    "fonts/alegreya-latin-400.woff2": {
      "name": "fonts/alegreya-latin-400.woff2",
      "path": "/var/lib/jenkins/agent-workdir/workspace/DWAPPS/pypi-upload/static/fonts/alegreya-latin-400.woff2",
      "publicPath": "/static/fonts/alegreya-latin-400.woff2"
    },
    "fonts/alegreya-latin-400italic.woff": {
      "name": "fonts/alegreya-latin-400italic.woff",
      "path": "/var/lib/jenkins/agent-workdir/workspace/DWAPPS/pypi-upload/static/fonts/alegreya-latin-400italic.woff",
      "publicPath": "/static/fonts/alegreya-latin-400italic.woff"
    },
    "fonts/alegreya-latin-400italic.woff2": {
      "name": "fonts/alegreya-latin-400italic.woff2",
      "path": "/var/lib/jenkins/agent-workdir/workspace/DWAPPS/pypi-upload/static/fonts/alegreya-latin-400italic.woff2",
      "publicPath": "/static/fonts/alegreya-latin-400italic.woff2"
    },
    "fonts/alegreya-latin-500.woff": {
      "name": "fonts/alegreya-latin-500.woff",
      "path": "/var/lib/jenkins/agent-workdir/workspace/DWAPPS/pypi-upload/static/fonts/alegreya-latin-500.woff",
      "publicPath": "/static/fonts/alegreya-latin-500.woff"
    },
    "fonts/alegreya-latin-500.woff2": {
      "name": "fonts/alegreya-latin-500.woff2",
      "path": "/var/lib/jenkins/agent-workdir/workspace/DWAPPS/pypi-upload/static/fonts/alegreya-latin-500.woff2",
      "publicPath": "/static/fonts/alegreya-latin-500.woff2"
    },
    "fonts/alegreya-latin-500italic.woff": {
      "name": "fonts/alegreya-latin-500italic.woff",
      "path": "/var/lib/jenkins/agent-workdir/workspace/DWAPPS/pypi-upload/static/fonts/alegreya-latin-500italic.woff",
      "publicPath": "/static/fonts/alegreya-latin-500italic.woff"
    },
    "fonts/alegreya-latin-500italic.woff2": {
      "name": "fonts/alegreya-latin-500italic.woff2",
      "path": "/var/lib/jenkins/agent-workdir/workspace/DWAPPS/pypi-upload/static/fonts/alegreya-latin-500italic.woff2",
      "publicPath": "/static/fonts/alegreya-latin-500italic.woff2"
    },
    "fonts/alegreya-latin-700.woff": {
      "name": "fonts/alegreya-latin-700.woff",
      "path": "/var/lib/jenkins/agent-workdir/workspace/DWAPPS/pypi-upload/static/fonts/alegreya-latin-700.woff",
      "publicPath": "/static/fonts/alegreya-latin-700.woff"
    },
    "fonts/alegreya-latin-700.woff2": {
      "name": "fonts/alegreya-latin-700.woff2",
      "path": "/var/lib/jenkins/agent-workdir/workspace/DWAPPS/pypi-upload/static/fonts/alegreya-latin-700.woff2",
      "publicPath": "/static/fonts/alegreya-latin-700.woff2"
    },
    "fonts/alegreya-latin-700italic.woff": {
      "name": "fonts/alegreya-latin-700italic.woff",
      "path": "/var/lib/jenkins/agent-workdir/workspace/DWAPPS/pypi-upload/static/fonts/alegreya-latin-700italic.woff",
      "publicPath": "/static/fonts/alegreya-latin-700italic.woff"
    },
    "fonts/alegreya-latin-700italic.woff2": {
      "name": "fonts/alegreya-latin-700italic.woff2",
      "path": "/var/lib/jenkins/agent-workdir/workspace/DWAPPS/pypi-upload/static/fonts/alegreya-latin-700italic.woff2",
      "publicPath": "/static/fonts/alegreya-latin-700italic.woff2"
    },
    "fonts/alegreya-latin-800.woff": {
      "name": "fonts/alegreya-latin-800.woff",
      "path": "/var/lib/jenkins/agent-workdir/workspace/DWAPPS/pypi-upload/static/fonts/alegreya-latin-800.woff",
      "publicPath": "/static/fonts/alegreya-latin-800.woff"
    },
    "fonts/alegreya-latin-800.woff2": {
      "name": "fonts/alegreya-latin-800.woff2",
      "path": "/var/lib/jenkins/agent-workdir/workspace/DWAPPS/pypi-upload/static/fonts/alegreya-latin-800.woff2",
      "publicPath": "/static/fonts/alegreya-latin-800.woff2"
    },
    "fonts/alegreya-latin-800italic.woff": {
      "name": "fonts/alegreya-latin-800italic.woff",
      "path": "/var/lib/jenkins/agent-workdir/workspace/DWAPPS/pypi-upload/static/fonts/alegreya-latin-800italic.woff",
      "publicPath": "/static/fonts/alegreya-latin-800italic.woff"
    },
    "fonts/alegreya-latin-800italic.woff2": {
      "name": "fonts/alegreya-latin-800italic.woff2",
      "path": "/var/lib/jenkins/agent-workdir/workspace/DWAPPS/pypi-upload/static/fonts/alegreya-latin-800italic.woff2",
      "publicPath": "/static/fonts/alegreya-latin-800italic.woff2"
    },
    "fonts/alegreya-latin-900.woff": {
      "name": "fonts/alegreya-latin-900.woff",
      "path": "/var/lib/jenkins/agent-workdir/workspace/DWAPPS/pypi-upload/static/fonts/alegreya-latin-900.woff",
      "publicPath": "/static/fonts/alegreya-latin-900.woff"
    },
    "fonts/alegreya-latin-900.woff2": {
      "name": "fonts/alegreya-latin-900.woff2",
      "path": "/var/lib/jenkins/agent-workdir/workspace/DWAPPS/pypi-upload/static/fonts/alegreya-latin-900.woff2",
      "publicPath": "/static/fonts/alegreya-latin-900.woff2"
    },
    "fonts/alegreya-latin-900italic.woff": {
      "name": "fonts/alegreya-latin-900italic.woff",
      "path": "/var/lib/jenkins/agent-workdir/workspace/DWAPPS/pypi-upload/static/fonts/alegreya-latin-900italic.woff",
      "publicPath": "/static/fonts/alegreya-latin-900italic.woff"
    },
    "fonts/alegreya-latin-900italic.woff2": {
      "name": "fonts/alegreya-latin-900italic.woff2",
      "path": "/var/lib/jenkins/agent-workdir/workspace/DWAPPS/pypi-upload/static/fonts/alegreya-latin-900italic.woff2",
      "publicPath": "/static/fonts/alegreya-latin-900italic.woff2"
    },
    "fonts/alegreya-sans-latin-100.woff": {
      "name": "fonts/alegreya-sans-latin-100.woff",
      "path": "/var/lib/jenkins/agent-workdir/workspace/DWAPPS/pypi-upload/static/fonts/alegreya-sans-latin-100.woff",
      "publicPath": "/static/fonts/alegreya-sans-latin-100.woff"
    },
    "fonts/alegreya-sans-latin-100.woff2": {
      "name": "fonts/alegreya-sans-latin-100.woff2",
      "path": "/var/lib/jenkins/agent-workdir/workspace/DWAPPS/pypi-upload/static/fonts/alegreya-sans-latin-100.woff2",
      "publicPath": "/static/fonts/alegreya-sans-latin-100.woff2"
    },
    "fonts/alegreya-sans-latin-100italic.woff": {
      "name": "fonts/alegreya-sans-latin-100italic.woff",
      "path": "/var/lib/jenkins/agent-workdir/workspace/DWAPPS/pypi-upload/static/fonts/alegreya-sans-latin-100italic.woff",
      "publicPath": "/static/fonts/alegreya-sans-latin-100italic.woff"
    },
    "fonts/alegreya-sans-latin-100italic.woff2": {
      "name": "fonts/alegreya-sans-latin-100italic.woff2",
      "path": "/var/lib/jenkins/agent-workdir/workspace/DWAPPS/pypi-upload/static/fonts/alegreya-sans-latin-100italic.woff2",
      "publicPath": "/static/fonts/alegreya-sans-latin-100italic.woff2"
    },
    "fonts/alegreya-sans-latin-300.woff": {
      "name": "fonts/alegreya-sans-latin-300.woff",
      "path": "/var/lib/jenkins/agent-workdir/workspace/DWAPPS/pypi-upload/static/fonts/alegreya-sans-latin-300.woff",
      "publicPath": "/static/fonts/alegreya-sans-latin-300.woff"
    },
    "fonts/alegreya-sans-latin-300.woff2": {
      "name": "fonts/alegreya-sans-latin-300.woff2",
      "path": "/var/lib/jenkins/agent-workdir/workspace/DWAPPS/pypi-upload/static/fonts/alegreya-sans-latin-300.woff2",
      "publicPath": "/static/fonts/alegreya-sans-latin-300.woff2"
    },
    "fonts/alegreya-sans-latin-300italic.woff": {
      "name": "fonts/alegreya-sans-latin-300italic.woff",
      "path": "/var/lib/jenkins/agent-workdir/workspace/DWAPPS/pypi-upload/static/fonts/alegreya-sans-latin-300italic.woff",
      "publicPath": "/static/fonts/alegreya-sans-latin-300italic.woff"
    },
    "fonts/alegreya-sans-latin-300italic.woff2": {
      "name": "fonts/alegreya-sans-latin-300italic.woff2",
      "path": "/var/lib/jenkins/agent-workdir/workspace/DWAPPS/pypi-upload/static/fonts/alegreya-sans-latin-300italic.woff2",
      "publicPath": "/static/fonts/alegreya-sans-latin-300italic.woff2"
    },
    "fonts/alegreya-sans-latin-400.woff": {
      "name": "fonts/alegreya-sans-latin-400.woff",
      "path": "/var/lib/jenkins/agent-workdir/workspace/DWAPPS/pypi-upload/static/fonts/alegreya-sans-latin-400.woff",
      "publicPath": "/static/fonts/alegreya-sans-latin-400.woff"
    },
    "fonts/alegreya-sans-latin-400.woff2": {
      "name": "fonts/alegreya-sans-latin-400.woff2",
      "path": "/var/lib/jenkins/agent-workdir/workspace/DWAPPS/pypi-upload/static/fonts/alegreya-sans-latin-400.woff2",
      "publicPath": "/static/fonts/alegreya-sans-latin-400.woff2"
    },
    "fonts/alegreya-sans-latin-400italic.woff": {
      "name": "fonts/alegreya-sans-latin-400italic.woff",
      "path": "/var/lib/jenkins/agent-workdir/workspace/DWAPPS/pypi-upload/static/fonts/alegreya-sans-latin-400italic.woff",
      "publicPath": "/static/fonts/alegreya-sans-latin-400italic.woff"
    },
    "fonts/alegreya-sans-latin-400italic.woff2": {
      "name": "fonts/alegreya-sans-latin-400italic.woff2",
      "path": "/var/lib/jenkins/agent-workdir/workspace/DWAPPS/pypi-upload/static/fonts/alegreya-sans-latin-400italic.woff2",
      "publicPath": "/static/fonts/alegreya-sans-latin-400italic.woff2"
    },
    "fonts/alegreya-sans-latin-500.woff": {
      "name": "fonts/alegreya-sans-latin-500.woff",
      "path": "/var/lib/jenkins/agent-workdir/workspace/DWAPPS/pypi-upload/static/fonts/alegreya-sans-latin-500.woff",
      "publicPath": "/static/fonts/alegreya-sans-latin-500.woff"
    },
    "fonts/alegreya-sans-latin-500.woff2": {
      "name": "fonts/alegreya-sans-latin-500.woff2",
      "path": "/var/lib/jenkins/agent-workdir/workspace/DWAPPS/pypi-upload/static/fonts/alegreya-sans-latin-500.woff2",
      "publicPath": "/static/fonts/alegreya-sans-latin-500.woff2"
    },
    "fonts/alegreya-sans-latin-500italic.woff": {
      "name": "fonts/alegreya-sans-latin-500italic.woff",
      "path": "/var/lib/jenkins/agent-workdir/workspace/DWAPPS/pypi-upload/static/fonts/alegreya-sans-latin-500italic.woff",
      "publicPath": "/static/fonts/alegreya-sans-latin-500italic.woff"
    },
    "fonts/alegreya-sans-latin-500italic.woff2": {
      "name": "fonts/alegreya-sans-latin-500italic.woff2",
      "path": "/var/lib/jenkins/agent-workdir/workspace/DWAPPS/pypi-upload/static/fonts/alegreya-sans-latin-500italic.woff2",
      "publicPath": "/static/fonts/alegreya-sans-latin-500italic.woff2"
    },
    "fonts/alegreya-sans-latin-700.woff": {
      "name": "fonts/alegreya-sans-latin-700.woff",
      "path": "/var/lib/jenkins/agent-workdir/workspace/DWAPPS/pypi-upload/static/fonts/alegreya-sans-latin-700.woff",
      "publicPath": "/static/fonts/alegreya-sans-latin-700.woff"
    },
    "fonts/alegreya-sans-latin-700.woff2": {
      "name": "fonts/alegreya-sans-latin-700.woff2",
      "path": "/var/lib/jenkins/agent-workdir/workspace/DWAPPS/pypi-upload/static/fonts/alegreya-sans-latin-700.woff2",
      "publicPath": "/static/fonts/alegreya-sans-latin-700.woff2"
    },
    "fonts/alegreya-sans-latin-700italic.woff": {
      "name": "fonts/alegreya-sans-latin-700italic.woff",
      "path": "/var/lib/jenkins/agent-workdir/workspace/DWAPPS/pypi-upload/static/fonts/alegreya-sans-latin-700italic.woff",
      "publicPath": "/static/fonts/alegreya-sans-latin-700italic.woff"
    },
    "fonts/alegreya-sans-latin-700italic.woff2": {
      "name": "fonts/alegreya-sans-latin-700italic.woff2",
      "path": "/var/lib/jenkins/agent-workdir/workspace/DWAPPS/pypi-upload/static/fonts/alegreya-sans-latin-700italic.woff2",
      "publicPath": "/static/fonts/alegreya-sans-latin-700italic.woff2"
    },
    "fonts/alegreya-sans-latin-800.woff": {
      "name": "fonts/alegreya-sans-latin-800.woff",
      "path": "/var/lib/jenkins/agent-workdir/workspace/DWAPPS/pypi-upload/static/fonts/alegreya-sans-latin-800.woff",
      "publicPath": "/static/fonts/alegreya-sans-latin-800.woff"
    },
    "fonts/alegreya-sans-latin-800.woff2": {
      "name": "fonts/alegreya-sans-latin-800.woff2",
      "path": "/var/lib/jenkins/agent-workdir/workspace/DWAPPS/pypi-upload/static/fonts/alegreya-sans-latin-800.woff2",
      "publicPath": "/static/fonts/alegreya-sans-latin-800.woff2"
    },
    "fonts/alegreya-sans-latin-800italic.woff": {
      "name": "fonts/alegreya-sans-latin-800italic.woff",
      "path": "/var/lib/jenkins/agent-workdir/workspace/DWAPPS/pypi-upload/static/fonts/alegreya-sans-latin-800italic.woff",
      "publicPath": "/static/fonts/alegreya-sans-latin-800italic.woff"
    },
    "fonts/alegreya-sans-latin-800italic.woff2": {
      "name": "fonts/alegreya-sans-latin-800italic.woff2",
      "path": "/var/lib/jenkins/agent-workdir/workspace/DWAPPS/pypi-upload/static/fonts/alegreya-sans-latin-800italic.woff2",
      "publicPath": "/static/fonts/alegreya-sans-latin-800italic.woff2"
    },
    "fonts/alegreya-sans-latin-900.woff": {
      "name": "fonts/alegreya-sans-latin-900.woff",
      "path": "/var/lib/jenkins/agent-workdir/workspace/DWAPPS/pypi-upload/static/fonts/alegreya-sans-latin-900.woff",
      "publicPath": "/static/fonts/alegreya-sans-latin-900.woff"
    },
    "fonts/alegreya-sans-latin-900.woff2": {
      "name": "fonts/alegreya-sans-latin-900.woff2",
      "path": "/var/lib/jenkins/agent-workdir/workspace/DWAPPS/pypi-upload/static/fonts/alegreya-sans-latin-900.woff2",
      "publicPath": "/static/fonts/alegreya-sans-latin-900.woff2"
    },
    "fonts/alegreya-sans-latin-900italic.woff": {
      "name": "fonts/alegreya-sans-latin-900italic.woff",
      "path": "/var/lib/jenkins/agent-workdir/workspace/DWAPPS/pypi-upload/static/fonts/alegreya-sans-latin-900italic.woff",
      "publicPath": "/static/fonts/alegreya-sans-latin-900italic.woff"
    },
    "fonts/alegreya-sans-latin-900italic.woff2": {
      "name": "fonts/alegreya-sans-latin-900italic.woff2",
      "path": "/var/lib/jenkins/agent-workdir/workspace/DWAPPS/pypi-upload/static/fonts/alegreya-sans-latin-900italic.woff2",
      "publicPath": "/static/fonts/alegreya-sans-latin-900italic.woff2"
    },
    "fonts/materialdesignicons-webfont.eot": {
      "name": "fonts/materialdesignicons-webfont.eot",
      "path": "/var/lib/jenkins/agent-workdir/workspace/DWAPPS/pypi-upload/static/fonts/materialdesignicons-webfont.eot",
      "publicPath": "/static/fonts/materialdesignicons-webfont.eot"
    },
    "fonts/materialdesignicons-webfont.eot?v=7.3.67": {
      "name": "fonts/materialdesignicons-webfont.eot?v=7.3.67",
      "path": "/var/lib/jenkins/agent-workdir/workspace/DWAPPS/pypi-upload/static/fonts/materialdesignicons-webfont.eot",
      "publicPath": "/static/fonts/materialdesignicons-webfont.eot?v=7.3.67"
    },
    "fonts/materialdesignicons-webfont.ttf?v=7.3.67": {
      "name": "fonts/materialdesignicons-webfont.ttf?v=7.3.67",
      "path": "/var/lib/jenkins/agent-workdir/workspace/DWAPPS/pypi-upload/static/fonts/materialdesignicons-webfont.ttf",
      "publicPath": "/static/fonts/materialdesignicons-webfont.ttf?v=7.3.67"
    },
    "fonts/materialdesignicons-webfont.woff?v=7.3.67": {
      "name": "fonts/materialdesignicons-webfont.woff?v=7.3.67",
      "path": "/var/lib/jenkins/agent-workdir/workspace/DWAPPS/pypi-upload/static/fonts/materialdesignicons-webfont.woff",
      "publicPath": "/static/fonts/materialdesignicons-webfont.woff?v=7.3.67"
    },
    "fonts/materialdesignicons-webfont.woff2?v=7.3.67": {
      "name": "fonts/materialdesignicons-webfont.woff2?v=7.3.67",
      "path": "/var/lib/jenkins/agent-workdir/workspace/DWAPPS/pypi-upload/static/fonts/materialdesignicons-webfont.woff2",
      "publicPath": "/static/fonts/materialdesignicons-webfont.woff2?v=7.3.67"
    },
    "fonts/MathJax_AMS-Regular.woff": {
      "name": "fonts/MathJax_AMS-Regular.woff",
      "path": "/var/lib/jenkins/agent-workdir/workspace/DWAPPS/pypi-upload/static/fonts/MathJax_AMS-Regular.woff",
      "publicPath": "/static/fonts/MathJax_AMS-Regular.woff"
    },
    "fonts/MathJax_Calligraphic-Bold.woff": {
      "name": "fonts/MathJax_Calligraphic-Bold.woff",
      "path": "/var/lib/jenkins/agent-workdir/workspace/DWAPPS/pypi-upload/static/fonts/MathJax_Calligraphic-Bold.woff",
      "publicPath": "/static/fonts/MathJax_Calligraphic-Bold.woff"
    },
    "fonts/MathJax_Calligraphic-Regular.woff": {
      "name": "fonts/MathJax_Calligraphic-Regular.woff",
      "path": "/var/lib/jenkins/agent-workdir/workspace/DWAPPS/pypi-upload/static/fonts/MathJax_Calligraphic-Regular.woff",
      "publicPath": "/static/fonts/MathJax_Calligraphic-Regular.woff"
    },
    "fonts/MathJax_Fraktur-Bold.woff": {
      "name": "fonts/MathJax_Fraktur-Bold.woff",
      "path": "/var/lib/jenkins/agent-workdir/workspace/DWAPPS/pypi-upload/static/fonts/MathJax_Fraktur-Bold.woff",
      "publicPath": "/static/fonts/MathJax_Fraktur-Bold.woff"
    },
    "fonts/MathJax_Fraktur-Regular.woff": {
      "name": "fonts/MathJax_Fraktur-Regular.woff",
      "path": "/var/lib/jenkins/agent-workdir/workspace/DWAPPS/pypi-upload/static/fonts/MathJax_Fraktur-Regular.woff",
      "publicPath": "/static/fonts/MathJax_Fraktur-Regular.woff"
    },
    "fonts/MathJax_Main-Bold.woff": {
      "name": "fonts/MathJax_Main-Bold.woff",
      "path": "/var/lib/jenkins/agent-workdir/workspace/DWAPPS/pypi-upload/static/fonts/MathJax_Main-Bold.woff",
      "publicPath": "/static/fonts/MathJax_Main-Bold.woff"
    },
    "fonts/MathJax_Main-Italic.woff": {
      "name": "fonts/MathJax_Main-Italic.woff",
      "path": "/var/lib/jenkins/agent-workdir/workspace/DWAPPS/pypi-upload/static/fonts/MathJax_Main-Italic.woff",
      "publicPath": "/static/fonts/MathJax_Main-Italic.woff"
    },
    "fonts/MathJax_Main-Regular.woff": {
      "name": "fonts/MathJax_Main-Regular.woff",
      "path": "/var/lib/jenkins/agent-workdir/workspace/DWAPPS/pypi-upload/static/fonts/MathJax_Main-Regular.woff",
      "publicPath": "/static/fonts/MathJax_Main-Regular.woff"
    },
    "fonts/MathJax_Math-BoldItalic.woff": {
      "name": "fonts/MathJax_Math-BoldItalic.woff",
      "path": "/var/lib/jenkins/agent-workdir/workspace/DWAPPS/pypi-upload/static/fonts/MathJax_Math-BoldItalic.woff",
      "publicPath": "/static/fonts/MathJax_Math-BoldItalic.woff"
    },
    "fonts/MathJax_Math-Italic.woff": {
      "name": "fonts/MathJax_Math-Italic.woff",
      "path": "/var/lib/jenkins/agent-workdir/workspace/DWAPPS/pypi-upload/static/fonts/MathJax_Math-Italic.woff",
      "publicPath": "/static/fonts/MathJax_Math-Italic.woff"
    },
    "fonts/MathJax_Math-Regular.woff": {
      "name": "fonts/MathJax_Math-Regular.woff",
      "path": "/var/lib/jenkins/agent-workdir/workspace/DWAPPS/pypi-upload/static/fonts/MathJax_Math-Regular.woff",
      "publicPath": "/static/fonts/MathJax_Math-Regular.woff"
    },
    "fonts/MathJax_SansSerif-Bold.woff": {
      "name": "fonts/MathJax_SansSerif-Bold.woff",
      "path": "/var/lib/jenkins/agent-workdir/workspace/DWAPPS/pypi-upload/static/fonts/MathJax_SansSerif-Bold.woff",
      "publicPath": "/static/fonts/MathJax_SansSerif-Bold.woff"
    },
    "fonts/MathJax_SansSerif-Italic.woff": {
      "name": "fonts/MathJax_SansSerif-Italic.woff",
      "path": "/var/lib/jenkins/agent-workdir/workspace/DWAPPS/pypi-upload/static/fonts/MathJax_SansSerif-Italic.woff",
      "publicPath": "/static/fonts/MathJax_SansSerif-Italic.woff"
    },
    "fonts/MathJax_SansSerif-Regular.woff": {
      "name": "fonts/MathJax_SansSerif-Regular.woff",
      "path": "/var/lib/jenkins/agent-workdir/workspace/DWAPPS/pypi-upload/static/fonts/MathJax_SansSerif-Regular.woff",
      "publicPath": "/static/fonts/MathJax_SansSerif-Regular.woff"
    },
    "fonts/MathJax_Script-Regular.woff": {
      "name": "fonts/MathJax_Script-Regular.woff",
      "path": "/var/lib/jenkins/agent-workdir/workspace/DWAPPS/pypi-upload/static/fonts/MathJax_Script-Regular.woff",
      "publicPath": "/static/fonts/MathJax_Script-Regular.woff"
    },
    "fonts/MathJax_Size1-Regular.woff": {
      "name": "fonts/MathJax_Size1-Regular.woff",
      "path": "/var/lib/jenkins/agent-workdir/workspace/DWAPPS/pypi-upload/static/fonts/MathJax_Size1-Regular.woff",
      "publicPath": "/static/fonts/MathJax_Size1-Regular.woff"
    },
    "fonts/MathJax_Size2-Regular.woff": {
      "name": "fonts/MathJax_Size2-Regular.woff",
      "path": "/var/lib/jenkins/agent-workdir/workspace/DWAPPS/pypi-upload/static/fonts/MathJax_Size2-Regular.woff",
      "publicPath": "/static/fonts/MathJax_Size2-Regular.woff"
    },
    "fonts/MathJax_Size3-Regular.woff": {
      "name": "fonts/MathJax_Size3-Regular.woff",
      "path": "/var/lib/jenkins/agent-workdir/workspace/DWAPPS/pypi-upload/static/fonts/MathJax_Size3-Regular.woff",
      "publicPath": "/static/fonts/MathJax_Size3-Regular.woff"
    },
    "fonts/MathJax_Size4-Regular.woff": {
      "name": "fonts/MathJax_Size4-Regular.woff",
      "path": "/var/lib/jenkins/agent-workdir/workspace/DWAPPS/pypi-upload/static/fonts/MathJax_Size4-Regular.woff",
      "publicPath": "/static/fonts/MathJax_Size4-Regular.woff"
    },
    "fonts/MathJax_Typewriter-Regular.woff": {
      "name": "fonts/MathJax_Typewriter-Regular.woff",
      "path": "/var/lib/jenkins/agent-workdir/workspace/DWAPPS/pypi-upload/static/fonts/MathJax_Typewriter-Regular.woff",
      "publicPath": "/static/fonts/MathJax_Typewriter-Regular.woff"
    },
    "fonts/MathJax_Vector-Bold.woff": {
      "name": "fonts/MathJax_Vector-Bold.woff",
      "path": "/var/lib/jenkins/agent-workdir/workspace/DWAPPS/pypi-upload/static/fonts/MathJax_Vector-Bold.woff",
      "publicPath": "/static/fonts/MathJax_Vector-Bold.woff"
    },
    "fonts/MathJax_Vector-Regular.woff": {
      "name": "fonts/MathJax_Vector-Regular.woff",
      "path": "/var/lib/jenkins/agent-workdir/workspace/DWAPPS/pypi-upload/static/fonts/MathJax_Vector-Regular.woff",
      "publicPath": "/static/fonts/MathJax_Vector-Regular.woff"
    },
    "fonts/MathJax_Zero.woff": {
      "name": "fonts/MathJax_Zero.woff",
      "path": "/var/lib/jenkins/agent-workdir/workspace/DWAPPS/pypi-upload/static/fonts/MathJax_Zero.woff",
      "publicPath": "/static/fonts/MathJax_Zero.woff"
    },
    "img/thirdParty/chosen-sprite.png": {
      "name": "img/thirdParty/chosen-sprite.png",
      "path": "/var/lib/jenkins/agent-workdir/workspace/DWAPPS/pypi-upload/static/img/thirdParty/chosen-sprite.png",
      "publicPath": "/static/img/thirdParty/chosen-sprite.png"
    },
    "img/thirdParty/chosen-sprite@2x.png": {
      "name": "img/thirdParty/chosen-sprite@2x.png",
      "path": "/var/lib/jenkins/agent-workdir/workspace/DWAPPS/pypi-upload/static/img/thirdParty/chosen-sprite@2x.png",
      "publicPath": "/static/img/thirdParty/chosen-sprite@2x.png"
    },
    "js/add_forge_now.21032f552061af6cd558.js": {
      "name": "js/add_forge_now.21032f552061af6cd558.js",
      "path": "/var/lib/jenkins/agent-workdir/workspace/DWAPPS/pypi-upload/static/js/add_forge_now.21032f552061af6cd558.js",
      "publicPath": "/static/js/add_forge_now.21032f552061af6cd558.js"
    },
    "js/add_forge_now.21032f552061af6cd558.js.LICENSE.txt": {
      "name": "js/add_forge_now.21032f552061af6cd558.js.LICENSE.txt",
      "path": "/var/lib/jenkins/agent-workdir/workspace/DWAPPS/pypi-upload/static/js/add_forge_now.21032f552061af6cd558.js.LICENSE.txt",
      "publicPath": "/static/js/add_forge_now.21032f552061af6cd558.js.LICENSE.txt"
    },
    "js/add_forge_now.21032f552061af6cd558.js.map": {
      "name": "js/add_forge_now.21032f552061af6cd558.js.map",
      "path": "/var/lib/jenkins/agent-workdir/workspace/DWAPPS/pypi-upload/static/js/add_forge_now.21032f552061af6cd558.js.map",
      "publicPath": "/static/js/add_forge_now.21032f552061af6cd558.js.map"
    },
    "js/archive_coverage.e955d98f21846a838785.js": {
      "name": "js/archive_coverage.e955d98f21846a838785.js",
      "path": "/var/lib/jenkins/agent-workdir/workspace/DWAPPS/pypi-upload/static/js/archive_coverage.e955d98f21846a838785.js",
      "publicPath": "/static/js/archive_coverage.e955d98f21846a838785.js"
    },
    "js/archive_coverage.e955d98f21846a838785.js.map": {
      "name": "js/archive_coverage.e955d98f21846a838785.js.map",
      "path": "/var/lib/jenkins/agent-workdir/workspace/DWAPPS/pypi-upload/static/js/archive_coverage.e955d98f21846a838785.js.map",
      "publicPath": "/static/js/archive_coverage.e955d98f21846a838785.js.map"
    },
    "js/auth.64781668980b5f20a1fd.js": {
      "name": "js/auth.64781668980b5f20a1fd.js",
      "path": "/var/lib/jenkins/agent-workdir/workspace/DWAPPS/pypi-upload/static/js/auth.64781668980b5f20a1fd.js",
      "publicPath": "/static/js/auth.64781668980b5f20a1fd.js"
    },
    "js/auth.64781668980b5f20a1fd.js.LICENSE.txt": {
      "name": "js/auth.64781668980b5f20a1fd.js.LICENSE.txt",
      "path": "/var/lib/jenkins/agent-workdir/workspace/DWAPPS/pypi-upload/static/js/auth.64781668980b5f20a1fd.js.LICENSE.txt",
      "publicPath": "/static/js/auth.64781668980b5f20a1fd.js.LICENSE.txt"
    },
    "js/auth.64781668980b5f20a1fd.js.map": {
      "name": "js/auth.64781668980b5f20a1fd.js.map",
      "path": "/var/lib/jenkins/agent-workdir/workspace/DWAPPS/pypi-upload/static/js/auth.64781668980b5f20a1fd.js.map",
      "publicPath": "/static/js/auth.64781668980b5f20a1fd.js.map"
    },
    "js/badges.99c11ebc4ec0b97c6b7b.js": {
      "name": "js/badges.99c11ebc4ec0b97c6b7b.js",
      "path": "/var/lib/jenkins/agent-workdir/workspace/DWAPPS/pypi-upload/static/js/badges.99c11ebc4ec0b97c6b7b.js",
      "publicPath": "/static/js/badges.99c11ebc4ec0b97c6b7b.js"
    },
    "js/badges.99c11ebc4ec0b97c6b7b.js.map": {
      "name": "js/badges.99c11ebc4ec0b97c6b7b.js.map",
      "path": "/var/lib/jenkins/agent-workdir/workspace/DWAPPS/pypi-upload/static/js/badges.99c11ebc4ec0b97c6b7b.js.map",
      "publicPath": "/static/js/badges.99c11ebc4ec0b97c6b7b.js.map"
    },
    "js/browse.c99fe443e6c04ad9befa.js": {
      "name": "js/browse.c99fe443e6c04ad9befa.js",
      "path": "/var/lib/jenkins/agent-workdir/workspace/DWAPPS/pypi-upload/static/js/browse.c99fe443e6c04ad9befa.js",
      "publicPath": "/static/js/browse.c99fe443e6c04ad9befa.js"
    },
    "js/browse.c99fe443e6c04ad9befa.js.LICENSE.txt": {
      "name": "js/browse.c99fe443e6c04ad9befa.js.LICENSE.txt",
      "path": "/var/lib/jenkins/agent-workdir/workspace/DWAPPS/pypi-upload/static/js/browse.c99fe443e6c04ad9befa.js.LICENSE.txt",
      "publicPath": "/static/js/browse.c99fe443e6c04ad9befa.js.LICENSE.txt"
    },
    "js/browse.c99fe443e6c04ad9befa.js.map": {
      "name": "js/browse.c99fe443e6c04ad9befa.js.map",
      "path": "/var/lib/jenkins/agent-workdir/workspace/DWAPPS/pypi-upload/static/js/browse.c99fe443e6c04ad9befa.js.map",
      "publicPath": "/static/js/browse.c99fe443e6c04ad9befa.js.map"
    },
    "js/d3.6d00def267d14fb00f50.js": {
      "name": "js/d3.6d00def267d14fb00f50.js",
      "path": "/var/lib/jenkins/agent-workdir/workspace/DWAPPS/pypi-upload/static/js/d3.6d00def267d14fb00f50.js",
      "publicPath": "/static/js/d3.6d00def267d14fb00f50.js"
    },
    "js/d3.6d00def267d14fb00f50.js.map": {
      "name": "js/d3.6d00def267d14fb00f50.js.map",
      "path": "/var/lib/jenkins/agent-workdir/workspace/DWAPPS/pypi-upload/static/js/d3.6d00def267d14fb00f50.js.map",
      "publicPath": "/static/js/d3.6d00def267d14fb00f50.js.map"
    },
    "js/deposit.267c42c1e7244e8ffbba.js": {
      "name": "js/deposit.267c42c1e7244e8ffbba.js",
      "path": "/var/lib/jenkins/agent-workdir/workspace/DWAPPS/pypi-upload/static/js/deposit.267c42c1e7244e8ffbba.js",
      "publicPath": "/static/js/deposit.267c42c1e7244e8ffbba.js"
    },
    "js/deposit.267c42c1e7244e8ffbba.js.LICENSE.txt": {
      "name": "js/deposit.267c42c1e7244e8ffbba.js.LICENSE.txt",
      "path": "/var/lib/jenkins/agent-workdir/workspace/DWAPPS/pypi-upload/static/js/deposit.267c42c1e7244e8ffbba.js.LICENSE.txt",
      "publicPath": "/static/js/deposit.267c42c1e7244e8ffbba.js.LICENSE.txt"
    },
    "js/deposit.267c42c1e7244e8ffbba.js.map": {
      "name": "js/deposit.267c42c1e7244e8ffbba.js.map",
      "path": "/var/lib/jenkins/agent-workdir/workspace/DWAPPS/pypi-upload/static/js/deposit.267c42c1e7244e8ffbba.js.map",
      "publicPath": "/static/js/deposit.267c42c1e7244e8ffbba.js.map"
    },
    "js/guided_tour.97839a97f902a41b1aef.js": {
      "name": "js/guided_tour.97839a97f902a41b1aef.js",
      "path": "/var/lib/jenkins/agent-workdir/workspace/DWAPPS/pypi-upload/static/js/guided_tour.97839a97f902a41b1aef.js",
      "publicPath": "/static/js/guided_tour.97839a97f902a41b1aef.js"
    },
    "js/guided_tour.97839a97f902a41b1aef.js.LICENSE.txt": {
      "name": "js/guided_tour.97839a97f902a41b1aef.js.LICENSE.txt",
      "path": "/var/lib/jenkins/agent-workdir/workspace/DWAPPS/pypi-upload/static/js/guided_tour.97839a97f902a41b1aef.js.LICENSE.txt",
      "publicPath": "/static/js/guided_tour.97839a97f902a41b1aef.js.LICENSE.txt"
    },
    "js/guided_tour.97839a97f902a41b1aef.js.map": {
      "name": "js/guided_tour.97839a97f902a41b1aef.js.map",
      "path": "/var/lib/jenkins/agent-workdir/workspace/DWAPPS/pypi-upload/static/js/guided_tour.97839a97f902a41b1aef.js.map",
      "publicPath": "/static/js/guided_tour.97839a97f902a41b1aef.js.map"
    },
    "js/highlightjs.53844db75eee8e1dcd8b.js": {
      "name": "js/highlightjs.53844db75eee8e1dcd8b.js",
      "path": "/var/lib/jenkins/agent-workdir/workspace/DWAPPS/pypi-upload/static/js/highlightjs.53844db75eee8e1dcd8b.js",
      "publicPath": "/static/js/highlightjs.53844db75eee8e1dcd8b.js"
    },
    "js/highlightjs.53844db75eee8e1dcd8b.js.LICENSE.txt": {
      "name": "js/highlightjs.53844db75eee8e1dcd8b.js.LICENSE.txt",
      "path": "/var/lib/jenkins/agent-workdir/workspace/DWAPPS/pypi-upload/static/js/highlightjs.53844db75eee8e1dcd8b.js.LICENSE.txt",
      "publicPath": "/static/js/highlightjs.53844db75eee8e1dcd8b.js.LICENSE.txt"
    },
    "js/highlightjs.53844db75eee8e1dcd8b.js.map": {
      "name": "js/highlightjs.53844db75eee8e1dcd8b.js.map",
      "path": "/var/lib/jenkins/agent-workdir/workspace/DWAPPS/pypi-upload/static/js/highlightjs.53844db75eee8e1dcd8b.js.map",
      "publicPath": "/static/js/highlightjs.53844db75eee8e1dcd8b.js.map"
    },
    "js/mailmap.a5453f5d5fb705f0b4db.js": {
      "name": "js/mailmap.a5453f5d5fb705f0b4db.js",
      "path": "/var/lib/jenkins/agent-workdir/workspace/DWAPPS/pypi-upload/static/js/mailmap.a5453f5d5fb705f0b4db.js",
      "publicPath": "/static/js/mailmap.a5453f5d5fb705f0b4db.js"
    },
    "js/mailmap.a5453f5d5fb705f0b4db.js.LICENSE.txt": {
      "name": "js/mailmap.a5453f5d5fb705f0b4db.js.LICENSE.txt",
      "path": "/var/lib/jenkins/agent-workdir/workspace/DWAPPS/pypi-upload/static/js/mailmap.a5453f5d5fb705f0b4db.js.LICENSE.txt",
      "publicPath": "/static/js/mailmap.a5453f5d5fb705f0b4db.js.LICENSE.txt"
    },
    "js/mailmap.a5453f5d5fb705f0b4db.js.map": {
      "name": "js/mailmap.a5453f5d5fb705f0b4db.js.map",
      "path": "/var/lib/jenkins/agent-workdir/workspace/DWAPPS/pypi-upload/static/js/mailmap.a5453f5d5fb705f0b4db.js.map",
      "publicPath": "/static/js/mailmap.a5453f5d5fb705f0b4db.js.map"
    },
    "js/mathjax.e10bdd1491f1884e97f3.js": {
      "name": "js/mathjax.e10bdd1491f1884e97f3.js",
      "path": "/var/lib/jenkins/agent-workdir/workspace/DWAPPS/pypi-upload/static/js/mathjax.e10bdd1491f1884e97f3.js",
      "publicPath": "/static/js/mathjax.e10bdd1491f1884e97f3.js"
    },
    "js/mathjax.e10bdd1491f1884e97f3.js.map": {
      "name": "js/mathjax.e10bdd1491f1884e97f3.js.map",
      "path": "/var/lib/jenkins/agent-workdir/workspace/DWAPPS/pypi-upload/static/js/mathjax.e10bdd1491f1884e97f3.js.map",
      "publicPath": "/static/js/mathjax.e10bdd1491f1884e97f3.js.map"
    },
    "js/org.4748b9b5135a400ad2de.js": {
      "name": "js/org.4748b9b5135a400ad2de.js",
      "path": "/var/lib/jenkins/agent-workdir/workspace/DWAPPS/pypi-upload/static/js/org.4748b9b5135a400ad2de.js",
      "publicPath": "/static/js/org.4748b9b5135a400ad2de.js"
    },
    "js/org.4748b9b5135a400ad2de.js.map": {
      "name": "js/org.4748b9b5135a400ad2de.js.map",
      "path": "/var/lib/jenkins/agent-workdir/workspace/DWAPPS/pypi-upload/static/js/org.4748b9b5135a400ad2de.js.map",
      "publicPath": "/static/js/org.4748b9b5135a400ad2de.js.map"
    },
    "js/origin_visits.f0e6af0395574f498e2d.js": {
      "name": "js/origin_visits.f0e6af0395574f498e2d.js",
      "path": "/var/lib/jenkins/agent-workdir/workspace/DWAPPS/pypi-upload/static/js/origin_visits.f0e6af0395574f498e2d.js",
      "publicPath": "/static/js/origin_visits.f0e6af0395574f498e2d.js"
    },
    "js/origin_visits.f0e6af0395574f498e2d.js.LICENSE.txt": {
      "name": "js/origin_visits.f0e6af0395574f498e2d.js.LICENSE.txt",
      "path": "/var/lib/jenkins/agent-workdir/workspace/DWAPPS/pypi-upload/static/js/origin_visits.f0e6af0395574f498e2d.js.LICENSE.txt",
      "publicPath": "/static/js/origin_visits.f0e6af0395574f498e2d.js.LICENSE.txt"
    },
    "js/origin_visits.f0e6af0395574f498e2d.js.map": {
      "name": "js/origin_visits.f0e6af0395574f498e2d.js.map",
      "path": "/var/lib/jenkins/agent-workdir/workspace/DWAPPS/pypi-upload/static/js/origin_visits.f0e6af0395574f498e2d.js.map",
      "publicPath": "/static/js/origin_visits.f0e6af0395574f498e2d.js.map"
    },
    "js/pdf.worker.min.js": {
      "name": "js/pdf.worker.min.js",
      "path": "/var/lib/jenkins/agent-workdir/workspace/DWAPPS/pypi-upload/static/js/pdf.worker.min.js",
      "publicPath": "/static/js/pdf.worker.min.js"
    },
    "js/pdf.worker.min.js.LICENSE.txt": {
      "name": "js/pdf.worker.min.js.LICENSE.txt",
      "path": "/var/lib/jenkins/agent-workdir/workspace/DWAPPS/pypi-upload/static/js/pdf.worker.min.js.LICENSE.txt",
      "publicPath": "/static/js/pdf.worker.min.js.LICENSE.txt"
    },
    "js/pdfjs.bd1269732e4391ed4876.js": {
      "name": "js/pdfjs.bd1269732e4391ed4876.js",
      "path": "/var/lib/jenkins/agent-workdir/workspace/DWAPPS/pypi-upload/static/js/pdfjs.bd1269732e4391ed4876.js",
      "publicPath": "/static/js/pdfjs.bd1269732e4391ed4876.js"
    },
    "js/pdfjs.bd1269732e4391ed4876.js.map": {
      "name": "js/pdfjs.bd1269732e4391ed4876.js.map",
      "path": "/var/lib/jenkins/agent-workdir/workspace/DWAPPS/pypi-upload/static/js/pdfjs.bd1269732e4391ed4876.js.map",
      "publicPath": "/static/js/pdfjs.bd1269732e4391ed4876.js.map"
    },
    "js/revision.d8caaeb0863b9de15654.js": {
      "name": "js/revision.d8caaeb0863b9de15654.js",
      "path": "/var/lib/jenkins/agent-workdir/workspace/DWAPPS/pypi-upload/static/js/revision.d8caaeb0863b9de15654.js",
      "publicPath": "/static/js/revision.d8caaeb0863b9de15654.js"
    },
    "js/revision.d8caaeb0863b9de15654.js.LICENSE.txt": {
      "name": "js/revision.d8caaeb0863b9de15654.js.LICENSE.txt",
      "path": "/var/lib/jenkins/agent-workdir/workspace/DWAPPS/pypi-upload/static/js/revision.d8caaeb0863b9de15654.js.LICENSE.txt",
      "publicPath": "/static/js/revision.d8caaeb0863b9de15654.js.LICENSE.txt"
    },
    "js/revision.d8caaeb0863b9de15654.js.map": {
      "name": "js/revision.d8caaeb0863b9de15654.js.map",
      "path": "/var/lib/jenkins/agent-workdir/workspace/DWAPPS/pypi-upload/static/js/revision.d8caaeb0863b9de15654.js.map",
      "publicPath": "/static/js/revision.d8caaeb0863b9de15654.js.map"
    },
    "js/save_code_now.acfd49f79f3cf43f4aed.js": {
      "name": "js/save_code_now.acfd49f79f3cf43f4aed.js",
      "path": "/var/lib/jenkins/agent-workdir/workspace/DWAPPS/pypi-upload/static/js/save_code_now.acfd49f79f3cf43f4aed.js",
      "publicPath": "/static/js/save_code_now.acfd49f79f3cf43f4aed.js"
    },
    "js/save_code_now.acfd49f79f3cf43f4aed.js.LICENSE.txt": {
      "name": "js/save_code_now.acfd49f79f3cf43f4aed.js.LICENSE.txt",
      "path": "/var/lib/jenkins/agent-workdir/workspace/DWAPPS/pypi-upload/static/js/save_code_now.acfd49f79f3cf43f4aed.js.LICENSE.txt",
      "publicPath": "/static/js/save_code_now.acfd49f79f3cf43f4aed.js.LICENSE.txt"
    },
    "js/save_code_now.acfd49f79f3cf43f4aed.js.map": {
      "name": "js/save_code_now.acfd49f79f3cf43f4aed.js.map",
      "path": "/var/lib/jenkins/agent-workdir/workspace/DWAPPS/pypi-upload/static/js/save_code_now.acfd49f79f3cf43f4aed.js.map",
      "publicPath": "/static/js/save_code_now.acfd49f79f3cf43f4aed.js.map"
    },
    "js/showdown.2331ae28aa1fba11e39f.js": {
      "name": "js/showdown.2331ae28aa1fba11e39f.js",
      "path": "/var/lib/jenkins/agent-workdir/workspace/DWAPPS/pypi-upload/static/js/showdown.2331ae28aa1fba11e39f.js",
      "publicPath": "/static/js/showdown.2331ae28aa1fba11e39f.js"
    },
    "js/showdown.2331ae28aa1fba11e39f.js.LICENSE.txt": {
      "name": "js/showdown.2331ae28aa1fba11e39f.js.LICENSE.txt",
      "path": "/var/lib/jenkins/agent-workdir/workspace/DWAPPS/pypi-upload/static/js/showdown.2331ae28aa1fba11e39f.js.LICENSE.txt",
      "publicPath": "/static/js/showdown.2331ae28aa1fba11e39f.js.LICENSE.txt"
    },
    "js/showdown.2331ae28aa1fba11e39f.js.map": {
      "name": "js/showdown.2331ae28aa1fba11e39f.js.map",
      "path": "/var/lib/jenkins/agent-workdir/workspace/DWAPPS/pypi-upload/static/js/showdown.2331ae28aa1fba11e39f.js.map",
      "publicPath": "/static/js/showdown.2331ae28aa1fba11e39f.js.map"
    },
    "js/vault.f4b754ca799d392e487f.js": {
      "name": "js/vault.f4b754ca799d392e487f.js",
      "path": "/var/lib/jenkins/agent-workdir/workspace/DWAPPS/pypi-upload/static/js/vault.f4b754ca799d392e487f.js",
      "publicPath": "/static/js/vault.f4b754ca799d392e487f.js"
    },
    "js/vault.f4b754ca799d392e487f.js.LICENSE.txt": {
      "name": "js/vault.f4b754ca799d392e487f.js.LICENSE.txt",
      "path": "/var/lib/jenkins/agent-workdir/workspace/DWAPPS/pypi-upload/static/js/vault.f4b754ca799d392e487f.js.LICENSE.txt",
      "publicPath": "/static/js/vault.f4b754ca799d392e487f.js.LICENSE.txt"
    },
    "js/vault.f4b754ca799d392e487f.js.map": {
      "name": "js/vault.f4b754ca799d392e487f.js.map",
      "path": "/var/lib/jenkins/agent-workdir/workspace/DWAPPS/pypi-upload/static/js/vault.f4b754ca799d392e487f.js.map",
      "publicPath": "/static/js/vault.f4b754ca799d392e487f.js.map"
    },
    "js/vendors.a8296a202fec352cea1a.js": {
      "name": "js/vendors.a8296a202fec352cea1a.js",
      "path": "/var/lib/jenkins/agent-workdir/workspace/DWAPPS/pypi-upload/static/js/vendors.a8296a202fec352cea1a.js",
      "publicPath": "/static/js/vendors.a8296a202fec352cea1a.js"
    },
    "js/vendors.a8296a202fec352cea1a.js.LICENSE.txt": {
      "name": "js/vendors.a8296a202fec352cea1a.js.LICENSE.txt",
      "path": "/var/lib/jenkins/agent-workdir/workspace/DWAPPS/pypi-upload/static/js/vendors.a8296a202fec352cea1a.js.LICENSE.txt",
      "publicPath": "/static/js/vendors.a8296a202fec352cea1a.js.LICENSE.txt"
    },
    "js/vendors.a8296a202fec352cea1a.js.map": {
      "name": "js/vendors.a8296a202fec352cea1a.js.map",
      "path": "/var/lib/jenkins/agent-workdir/workspace/DWAPPS/pypi-upload/static/js/vendors.a8296a202fec352cea1a.js.map",
      "publicPath": "/static/js/vendors.a8296a202fec352cea1a.js.map"
    },
    "js/webapp.18f46dab79a10f146cc7.js": {
      "name": "js/webapp.18f46dab79a10f146cc7.js",
      "path": "/var/lib/jenkins/agent-workdir/workspace/DWAPPS/pypi-upload/static/js/webapp.18f46dab79a10f146cc7.js",
      "publicPath": "/static/js/webapp.18f46dab79a10f146cc7.js"
    },
    "js/webapp.18f46dab79a10f146cc7.js.LICENSE.txt": {
      "name": "js/webapp.18f46dab79a10f146cc7.js.LICENSE.txt",
      "path": "/var/lib/jenkins/agent-workdir/workspace/DWAPPS/pypi-upload/static/js/webapp.18f46dab79a10f146cc7.js.LICENSE.txt",
      "publicPath": "/static/js/webapp.18f46dab79a10f146cc7.js.LICENSE.txt"
    },
    "js/webapp.18f46dab79a10f146cc7.js.map": {
      "name": "js/webapp.18f46dab79a10f146cc7.js.map",
      "path": "/var/lib/jenkins/agent-workdir/workspace/DWAPPS/pypi-upload/static/js/webapp.18f46dab79a10f146cc7.js.map",
      "publicPath": "/static/js/webapp.18f46dab79a10f146cc7.js.map"
    },
    "robots.txt": {
      "name": "robots.txt",
      "path": "/var/lib/jenkins/agent-workdir/workspace/DWAPPS/pypi-upload/static/robots.txt",
      "publicPath": "/static/robots.txt"
    }
  },
  "chunks": {
    "add_forge_now": [
      "css/add_forge_now.4f93c9769bc36a247915.css",
      "js/add_forge_now.21032f552061af6cd558.js"
    ],
    "archive_coverage": [
      "css/archive_coverage.6573148e19d3c98015b4.css",
      "js/archive_coverage.e955d98f21846a838785.js"
    ],
    "auth": [
      "css/auth.0336a94c2c02b4b2a4f4.css",
      "js/auth.64781668980b5f20a1fd.js"
    ],
    "badges": [
      "css/badges.03c8b295a163a9306210.css",
      "js/badges.99c11ebc4ec0b97c6b7b.js"
    ],
    "browse": [
      "css/browse.f5afe9b68b860a92d393.css",
      "js/browse.c99fe443e6c04ad9befa.js"
    ],
    "deposit": [
      "js/deposit.267c42c1e7244e8ffbba.js"
    ],
    "guided_tour": [
      "css/guided_tour.1bfa315c78e66451b0b2.css",
      "js/guided_tour.97839a97f902a41b1aef.js"
    ],
    "mailmap": [
      "js/mailmap.a5453f5d5fb705f0b4db.js"
    ],
    "origin_visits": [
      "css/origin_visits.405bdab2e61c346d77f1.css",
      "js/origin_visits.f0e6af0395574f498e2d.js"
    ],
    "revision": [
      "css/revision.4f3cb8316771ce5cd8b1.css",
      "js/revision.d8caaeb0863b9de15654.js"
    ],
    "save_code_now": [
      "js/save_code_now.acfd49f79f3cf43f4aed.js"
    ],
    "vault": [
      "css/vault.25fc5883f848b48ffa5b.css",
      "js/vault.f4b754ca799d392e487f.js"
    ],
    "vendors": [
      "css/vendors.d0eb81594ae7205efdb0.css",
      "js/vendors.a8296a202fec352cea1a.js"
    ],
    "webapp": [
      "css/webapp.0041e30b97d702aceb6a.css",
      "js/webapp.18f46dab79a10f146cc7.js"
    ]
  },
  "publicPath": "/static/"
}