{
  "status": "done",
  "assets": {
    "css/add_forge_now.4f93c9769bc36a247915.css": {
      "name": "css/add_forge_now.4f93c9769bc36a247915.css",
      "path": "/var/lib/jenkins/workspace/DWAPPS/pypi-upload/static/css/add_forge_now.4f93c9769bc36a247915.css",
      "publicPath": "/static/css/add_forge_now.4f93c9769bc36a247915.css"
    },
    "css/add_forge_now.4f93c9769bc36a247915.css.map": {
      "name": "css/add_forge_now.4f93c9769bc36a247915.css.map",
      "path": "/var/lib/jenkins/workspace/DWAPPS/pypi-upload/static/css/add_forge_now.4f93c9769bc36a247915.css.map",
      "publicPath": "/static/css/add_forge_now.4f93c9769bc36a247915.css.map"
    },
    "css/archive_coverage.243fd0a38715dd7ff3e5.css": {
      "name": "css/archive_coverage.243fd0a38715dd7ff3e5.css",
      "path": "/var/lib/jenkins/workspace/DWAPPS/pypi-upload/static/css/archive_coverage.243fd0a38715dd7ff3e5.css",
      "publicPath": "/static/css/archive_coverage.243fd0a38715dd7ff3e5.css"
    },
    "css/archive_coverage.243fd0a38715dd7ff3e5.css.map": {
      "name": "css/archive_coverage.243fd0a38715dd7ff3e5.css.map",
      "path": "/var/lib/jenkins/workspace/DWAPPS/pypi-upload/static/css/archive_coverage.243fd0a38715dd7ff3e5.css.map",
      "publicPath": "/static/css/archive_coverage.243fd0a38715dd7ff3e5.css.map"
    },
    "css/auth.0336a94c2c02b4b2a4f4.css": {
      "name": "css/auth.0336a94c2c02b4b2a4f4.css",
      "path": "/var/lib/jenkins/workspace/DWAPPS/pypi-upload/static/css/auth.0336a94c2c02b4b2a4f4.css",
      "publicPath": "/static/css/auth.0336a94c2c02b4b2a4f4.css"
    },
    "css/auth.0336a94c2c02b4b2a4f4.css.map": {
      "name": "css/auth.0336a94c2c02b4b2a4f4.css.map",
      "path": "/var/lib/jenkins/workspace/DWAPPS/pypi-upload/static/css/auth.0336a94c2c02b4b2a4f4.css.map",
      "publicPath": "/static/css/auth.0336a94c2c02b4b2a4f4.css.map"
    },
    "css/browse.3381f65cfada5255789a.css": {
      "name": "css/browse.3381f65cfada5255789a.css",
      "path": "/var/lib/jenkins/workspace/DWAPPS/pypi-upload/static/css/browse.3381f65cfada5255789a.css",
      "publicPath": "/static/css/browse.3381f65cfada5255789a.css"
    },
    "css/browse.3381f65cfada5255789a.css.map": {
      "name": "css/browse.3381f65cfada5255789a.css.map",
      "path": "/var/lib/jenkins/workspace/DWAPPS/pypi-upload/static/css/browse.3381f65cfada5255789a.css.map",
      "publicPath": "/static/css/browse.3381f65cfada5255789a.css.map"
    },
    "css/guided_tour.877fa77fcebc36a05b5c.css": {
      "name": "css/guided_tour.877fa77fcebc36a05b5c.css",
      "path": "/var/lib/jenkins/workspace/DWAPPS/pypi-upload/static/css/guided_tour.877fa77fcebc36a05b5c.css",
      "publicPath": "/static/css/guided_tour.877fa77fcebc36a05b5c.css"
    },
    "css/guided_tour.877fa77fcebc36a05b5c.css.map": {
      "name": "css/guided_tour.877fa77fcebc36a05b5c.css.map",
      "path": "/var/lib/jenkins/workspace/DWAPPS/pypi-upload/static/css/guided_tour.877fa77fcebc36a05b5c.css.map",
      "publicPath": "/static/css/guided_tour.877fa77fcebc36a05b5c.css.map"
    },
    "css/highlightjs.ae43064ab38a65a04d81.css": {
      "name": "css/highlightjs.ae43064ab38a65a04d81.css",
      "path": "/var/lib/jenkins/workspace/DWAPPS/pypi-upload/static/css/highlightjs.ae43064ab38a65a04d81.css",
      "publicPath": "/static/css/highlightjs.ae43064ab38a65a04d81.css"
    },
    "css/highlightjs.ae43064ab38a65a04d81.css.map": {
      "name": "css/highlightjs.ae43064ab38a65a04d81.css.map",
      "path": "/var/lib/jenkins/workspace/DWAPPS/pypi-upload/static/css/highlightjs.ae43064ab38a65a04d81.css.map",
      "publicPath": "/static/css/highlightjs.ae43064ab38a65a04d81.css.map"
    },
    "css/org.6851b70c924e28f6bf51.css": {
      "name": "css/org.6851b70c924e28f6bf51.css",
      "path": "/var/lib/jenkins/workspace/DWAPPS/pypi-upload/static/css/org.6851b70c924e28f6bf51.css",
      "publicPath": "/static/css/org.6851b70c924e28f6bf51.css"
    },
    "css/org.6851b70c924e28f6bf51.css.map": {
      "name": "css/org.6851b70c924e28f6bf51.css.map",
      "path": "/var/lib/jenkins/workspace/DWAPPS/pypi-upload/static/css/org.6851b70c924e28f6bf51.css.map",
      "publicPath": "/static/css/org.6851b70c924e28f6bf51.css.map"
    },
    "css/origin_visits.f74f3ffcbbce22294008.css": {
      "name": "css/origin_visits.f74f3ffcbbce22294008.css",
      "path": "/var/lib/jenkins/workspace/DWAPPS/pypi-upload/static/css/origin_visits.f74f3ffcbbce22294008.css",
      "publicPath": "/static/css/origin_visits.f74f3ffcbbce22294008.css"
    },
    "css/origin_visits.f74f3ffcbbce22294008.css.map": {
      "name": "css/origin_visits.f74f3ffcbbce22294008.css.map",
      "path": "/var/lib/jenkins/workspace/DWAPPS/pypi-upload/static/css/origin_visits.f74f3ffcbbce22294008.css.map",
      "publicPath": "/static/css/origin_visits.f74f3ffcbbce22294008.css.map"
    },
    "css/revision.5ddd36d69e1760bfa29d.css": {
      "name": "css/revision.5ddd36d69e1760bfa29d.css",
      "path": "/var/lib/jenkins/workspace/DWAPPS/pypi-upload/static/css/revision.5ddd36d69e1760bfa29d.css",
      "publicPath": "/static/css/revision.5ddd36d69e1760bfa29d.css"
    },
    "css/revision.5ddd36d69e1760bfa29d.css.map": {
      "name": "css/revision.5ddd36d69e1760bfa29d.css.map",
      "path": "/var/lib/jenkins/workspace/DWAPPS/pypi-upload/static/css/revision.5ddd36d69e1760bfa29d.css.map",
      "publicPath": "/static/css/revision.5ddd36d69e1760bfa29d.css.map"
    },
    "css/showdown.426fbf6a7a6653fd4cbb.css": {
      "name": "css/showdown.426fbf6a7a6653fd4cbb.css",
      "path": "/var/lib/jenkins/workspace/DWAPPS/pypi-upload/static/css/showdown.426fbf6a7a6653fd4cbb.css",
      "publicPath": "/static/css/showdown.426fbf6a7a6653fd4cbb.css"
    },
    "css/showdown.426fbf6a7a6653fd4cbb.css.map": {
      "name": "css/showdown.426fbf6a7a6653fd4cbb.css.map",
      "path": "/var/lib/jenkins/workspace/DWAPPS/pypi-upload/static/css/showdown.426fbf6a7a6653fd4cbb.css.map",
      "publicPath": "/static/css/showdown.426fbf6a7a6653fd4cbb.css.map"
    },
    "css/vault.25fc5883f848b48ffa5b.css": {
      "name": "css/vault.25fc5883f848b48ffa5b.css",
      "path": "/var/lib/jenkins/workspace/DWAPPS/pypi-upload/static/css/vault.25fc5883f848b48ffa5b.css",
      "publicPath": "/static/css/vault.25fc5883f848b48ffa5b.css"
    },
    "css/vault.25fc5883f848b48ffa5b.css.map": {
      "name": "css/vault.25fc5883f848b48ffa5b.css.map",
      "path": "/var/lib/jenkins/workspace/DWAPPS/pypi-upload/static/css/vault.25fc5883f848b48ffa5b.css.map",
      "publicPath": "/static/css/vault.25fc5883f848b48ffa5b.css.map"
    },
    "css/vendors.dfce793c06269b88766c.css": {
      "name": "css/vendors.dfce793c06269b88766c.css",
      "path": "/var/lib/jenkins/workspace/DWAPPS/pypi-upload/static/css/vendors.dfce793c06269b88766c.css",
      "publicPath": "/static/css/vendors.dfce793c06269b88766c.css"
    },
    "css/vendors.dfce793c06269b88766c.css.map": {
      "name": "css/vendors.dfce793c06269b88766c.css.map",
      "path": "/var/lib/jenkins/workspace/DWAPPS/pypi-upload/static/css/vendors.dfce793c06269b88766c.css.map",
      "publicPath": "/static/css/vendors.dfce793c06269b88766c.css.map"
    },
    "css/webapp.a5ee322795df19e158b7.css": {
      "name": "css/webapp.a5ee322795df19e158b7.css",
      "path": "/var/lib/jenkins/workspace/DWAPPS/pypi-upload/static/css/webapp.a5ee322795df19e158b7.css",
      "publicPath": "/static/css/webapp.a5ee322795df19e158b7.css"
    },
    "css/webapp.a5ee322795df19e158b7.css.map": {
      "name": "css/webapp.a5ee322795df19e158b7.css.map",
      "path": "/var/lib/jenkins/workspace/DWAPPS/pypi-upload/static/css/webapp.a5ee322795df19e158b7.css.map",
      "publicPath": "/static/css/webapp.a5ee322795df19e158b7.css.map"
    },
    "fonts/alegreya-latin-400.woff": {
      "name": "fonts/alegreya-latin-400.woff",
      "path": "/var/lib/jenkins/workspace/DWAPPS/pypi-upload/static/fonts/alegreya-latin-400.woff",
      "publicPath": "/static/fonts/alegreya-latin-400.woff"
    },
    "fonts/alegreya-latin-400.woff2": {
      "name": "fonts/alegreya-latin-400.woff2",
      "path": "/var/lib/jenkins/workspace/DWAPPS/pypi-upload/static/fonts/alegreya-latin-400.woff2",
      "publicPath": "/static/fonts/alegreya-latin-400.woff2"
    },
    "fonts/alegreya-latin-400italic.woff": {
      "name": "fonts/alegreya-latin-400italic.woff",
      "path": "/var/lib/jenkins/workspace/DWAPPS/pypi-upload/static/fonts/alegreya-latin-400italic.woff",
      "publicPath": "/static/fonts/alegreya-latin-400italic.woff"
    },
    "fonts/alegreya-latin-400italic.woff2": {
      "name": "fonts/alegreya-latin-400italic.woff2",
      "path": "/var/lib/jenkins/workspace/DWAPPS/pypi-upload/static/fonts/alegreya-latin-400italic.woff2",
      "publicPath": "/static/fonts/alegreya-latin-400italic.woff2"
    },
    "fonts/alegreya-latin-500.woff": {
      "name": "fonts/alegreya-latin-500.woff",
      "path": "/var/lib/jenkins/workspace/DWAPPS/pypi-upload/static/fonts/alegreya-latin-500.woff",
      "publicPath": "/static/fonts/alegreya-latin-500.woff"
    },
    "fonts/alegreya-latin-500.woff2": {
      "name": "fonts/alegreya-latin-500.woff2",
      "path": "/var/lib/jenkins/workspace/DWAPPS/pypi-upload/static/fonts/alegreya-latin-500.woff2",
      "publicPath": "/static/fonts/alegreya-latin-500.woff2"
    },
    "fonts/alegreya-latin-500italic.woff": {
      "name": "fonts/alegreya-latin-500italic.woff",
      "path": "/var/lib/jenkins/workspace/DWAPPS/pypi-upload/static/fonts/alegreya-latin-500italic.woff",
      "publicPath": "/static/fonts/alegreya-latin-500italic.woff"
    },
    "fonts/alegreya-latin-500italic.woff2": {
      "name": "fonts/alegreya-latin-500italic.woff2",
      "path": "/var/lib/jenkins/workspace/DWAPPS/pypi-upload/static/fonts/alegreya-latin-500italic.woff2",
      "publicPath": "/static/fonts/alegreya-latin-500italic.woff2"
    },
    "fonts/alegreya-latin-700.woff": {
      "name": "fonts/alegreya-latin-700.woff",
      "path": "/var/lib/jenkins/workspace/DWAPPS/pypi-upload/static/fonts/alegreya-latin-700.woff",
      "publicPath": "/static/fonts/alegreya-latin-700.woff"
    },
    "fonts/alegreya-latin-700.woff2": {
      "name": "fonts/alegreya-latin-700.woff2",
      "path": "/var/lib/jenkins/workspace/DWAPPS/pypi-upload/static/fonts/alegreya-latin-700.woff2",
      "publicPath": "/static/fonts/alegreya-latin-700.woff2"
    },
    "fonts/alegreya-latin-700italic.woff": {
      "name": "fonts/alegreya-latin-700italic.woff",
      "path": "/var/lib/jenkins/workspace/DWAPPS/pypi-upload/static/fonts/alegreya-latin-700italic.woff",
      "publicPath": "/static/fonts/alegreya-latin-700italic.woff"
    },
    "fonts/alegreya-latin-700italic.woff2": {
      "name": "fonts/alegreya-latin-700italic.woff2",
      "path": "/var/lib/jenkins/workspace/DWAPPS/pypi-upload/static/fonts/alegreya-latin-700italic.woff2",
      "publicPath": "/static/fonts/alegreya-latin-700italic.woff2"
    },
    "fonts/alegreya-latin-800.woff": {
      "name": "fonts/alegreya-latin-800.woff",
      "path": "/var/lib/jenkins/workspace/DWAPPS/pypi-upload/static/fonts/alegreya-latin-800.woff",
      "publicPath": "/static/fonts/alegreya-latin-800.woff"
    },
    "fonts/alegreya-latin-800.woff2": {
      "name": "fonts/alegreya-latin-800.woff2",
      "path": "/var/lib/jenkins/workspace/DWAPPS/pypi-upload/static/fonts/alegreya-latin-800.woff2",
      "publicPath": "/static/fonts/alegreya-latin-800.woff2"
    },
    "fonts/alegreya-latin-800italic.woff": {
      "name": "fonts/alegreya-latin-800italic.woff",
      "path": "/var/lib/jenkins/workspace/DWAPPS/pypi-upload/static/fonts/alegreya-latin-800italic.woff",
      "publicPath": "/static/fonts/alegreya-latin-800italic.woff"
    },
    "fonts/alegreya-latin-800italic.woff2": {
      "name": "fonts/alegreya-latin-800italic.woff2",
      "path": "/var/lib/jenkins/workspace/DWAPPS/pypi-upload/static/fonts/alegreya-latin-800italic.woff2",
      "publicPath": "/static/fonts/alegreya-latin-800italic.woff2"
    },
    "fonts/alegreya-latin-900.woff": {
      "name": "fonts/alegreya-latin-900.woff",
      "path": "/var/lib/jenkins/workspace/DWAPPS/pypi-upload/static/fonts/alegreya-latin-900.woff",
      "publicPath": "/static/fonts/alegreya-latin-900.woff"
    },
    "fonts/alegreya-latin-900.woff2": {
      "name": "fonts/alegreya-latin-900.woff2",
      "path": "/var/lib/jenkins/workspace/DWAPPS/pypi-upload/static/fonts/alegreya-latin-900.woff2",
      "publicPath": "/static/fonts/alegreya-latin-900.woff2"
    },
    "fonts/alegreya-latin-900italic.woff": {
      "name": "fonts/alegreya-latin-900italic.woff",
      "path": "/var/lib/jenkins/workspace/DWAPPS/pypi-upload/static/fonts/alegreya-latin-900italic.woff",
      "publicPath": "/static/fonts/alegreya-latin-900italic.woff"
    },
    "fonts/alegreya-latin-900italic.woff2": {
      "name": "fonts/alegreya-latin-900italic.woff2",
      "path": "/var/lib/jenkins/workspace/DWAPPS/pypi-upload/static/fonts/alegreya-latin-900italic.woff2",
      "publicPath": "/static/fonts/alegreya-latin-900italic.woff2"
    },
    "fonts/alegreya-sans-latin-100.woff": {
      "name": "fonts/alegreya-sans-latin-100.woff",
      "path": "/var/lib/jenkins/workspace/DWAPPS/pypi-upload/static/fonts/alegreya-sans-latin-100.woff",
      "publicPath": "/static/fonts/alegreya-sans-latin-100.woff"
    },
    "fonts/alegreya-sans-latin-100.woff2": {
      "name": "fonts/alegreya-sans-latin-100.woff2",
      "path": "/var/lib/jenkins/workspace/DWAPPS/pypi-upload/static/fonts/alegreya-sans-latin-100.woff2",
      "publicPath": "/static/fonts/alegreya-sans-latin-100.woff2"
    },
    "fonts/alegreya-sans-latin-100italic.woff": {
      "name": "fonts/alegreya-sans-latin-100italic.woff",
      "path": "/var/lib/jenkins/workspace/DWAPPS/pypi-upload/static/fonts/alegreya-sans-latin-100italic.woff",
      "publicPath": "/static/fonts/alegreya-sans-latin-100italic.woff"
    },
    "fonts/alegreya-sans-latin-100italic.woff2": {
      "name": "fonts/alegreya-sans-latin-100italic.woff2",
      "path": "/var/lib/jenkins/workspace/DWAPPS/pypi-upload/static/fonts/alegreya-sans-latin-100italic.woff2",
      "publicPath": "/static/fonts/alegreya-sans-latin-100italic.woff2"
    },
    "fonts/alegreya-sans-latin-300.woff": {
      "name": "fonts/alegreya-sans-latin-300.woff",
      "path": "/var/lib/jenkins/workspace/DWAPPS/pypi-upload/static/fonts/alegreya-sans-latin-300.woff",
      "publicPath": "/static/fonts/alegreya-sans-latin-300.woff"
    },
    "fonts/alegreya-sans-latin-300.woff2": {
      "name": "fonts/alegreya-sans-latin-300.woff2",
      "path": "/var/lib/jenkins/workspace/DWAPPS/pypi-upload/static/fonts/alegreya-sans-latin-300.woff2",
      "publicPath": "/static/fonts/alegreya-sans-latin-300.woff2"
    },
    "fonts/alegreya-sans-latin-300italic.woff": {
      "name": "fonts/alegreya-sans-latin-300italic.woff",
      "path": "/var/lib/jenkins/workspace/DWAPPS/pypi-upload/static/fonts/alegreya-sans-latin-300italic.woff",
      "publicPath": "/static/fonts/alegreya-sans-latin-300italic.woff"
    },
    "fonts/alegreya-sans-latin-300italic.woff2": {
      "name": "fonts/alegreya-sans-latin-300italic.woff2",
      "path": "/var/lib/jenkins/workspace/DWAPPS/pypi-upload/static/fonts/alegreya-sans-latin-300italic.woff2",
      "publicPath": "/static/fonts/alegreya-sans-latin-300italic.woff2"
    },
    "fonts/alegreya-sans-latin-400.woff": {
      "name": "fonts/alegreya-sans-latin-400.woff",
      "path": "/var/lib/jenkins/workspace/DWAPPS/pypi-upload/static/fonts/alegreya-sans-latin-400.woff",
      "publicPath": "/static/fonts/alegreya-sans-latin-400.woff"
    },
    "fonts/alegreya-sans-latin-400.woff2": {
      "name": "fonts/alegreya-sans-latin-400.woff2",
      "path": "/var/lib/jenkins/workspace/DWAPPS/pypi-upload/static/fonts/alegreya-sans-latin-400.woff2",
      "publicPath": "/static/fonts/alegreya-sans-latin-400.woff2"
    },
    "fonts/alegreya-sans-latin-400italic.woff": {
      "name": "fonts/alegreya-sans-latin-400italic.woff",
      "path": "/var/lib/jenkins/workspace/DWAPPS/pypi-upload/static/fonts/alegreya-sans-latin-400italic.woff",
      "publicPath": "/static/fonts/alegreya-sans-latin-400italic.woff"
    },
    "fonts/alegreya-sans-latin-400italic.woff2": {
      "name": "fonts/alegreya-sans-latin-400italic.woff2",
      "path": "/var/lib/jenkins/workspace/DWAPPS/pypi-upload/static/fonts/alegreya-sans-latin-400italic.woff2",
      "publicPath": "/static/fonts/alegreya-sans-latin-400italic.woff2"
    },
    "fonts/alegreya-sans-latin-500.woff": {
      "name": "fonts/alegreya-sans-latin-500.woff",
      "path": "/var/lib/jenkins/workspace/DWAPPS/pypi-upload/static/fonts/alegreya-sans-latin-500.woff",
      "publicPath": "/static/fonts/alegreya-sans-latin-500.woff"
    },
    "fonts/alegreya-sans-latin-500.woff2": {
      "name": "fonts/alegreya-sans-latin-500.woff2",
      "path": "/var/lib/jenkins/workspace/DWAPPS/pypi-upload/static/fonts/alegreya-sans-latin-500.woff2",
      "publicPath": "/static/fonts/alegreya-sans-latin-500.woff2"
    },
    "fonts/alegreya-sans-latin-500italic.woff": {
      "name": "fonts/alegreya-sans-latin-500italic.woff",
      "path": "/var/lib/jenkins/workspace/DWAPPS/pypi-upload/static/fonts/alegreya-sans-latin-500italic.woff",
      "publicPath": "/static/fonts/alegreya-sans-latin-500italic.woff"
    },
    "fonts/alegreya-sans-latin-500italic.woff2": {
      "name": "fonts/alegreya-sans-latin-500italic.woff2",
      "path": "/var/lib/jenkins/workspace/DWAPPS/pypi-upload/static/fonts/alegreya-sans-latin-500italic.woff2",
      "publicPath": "/static/fonts/alegreya-sans-latin-500italic.woff2"
    },
    "fonts/alegreya-sans-latin-700.woff": {
      "name": "fonts/alegreya-sans-latin-700.woff",
      "path": "/var/lib/jenkins/workspace/DWAPPS/pypi-upload/static/fonts/alegreya-sans-latin-700.woff",
      "publicPath": "/static/fonts/alegreya-sans-latin-700.woff"
    },
    "fonts/alegreya-sans-latin-700.woff2": {
      "name": "fonts/alegreya-sans-latin-700.woff2",
      "path": "/var/lib/jenkins/workspace/DWAPPS/pypi-upload/static/fonts/alegreya-sans-latin-700.woff2",
      "publicPath": "/static/fonts/alegreya-sans-latin-700.woff2"
    },
    "fonts/alegreya-sans-latin-700italic.woff": {
      "name": "fonts/alegreya-sans-latin-700italic.woff",
      "path": "/var/lib/jenkins/workspace/DWAPPS/pypi-upload/static/fonts/alegreya-sans-latin-700italic.woff",
      "publicPath": "/static/fonts/alegreya-sans-latin-700italic.woff"
    },
    "fonts/alegreya-sans-latin-700italic.woff2": {
      "name": "fonts/alegreya-sans-latin-700italic.woff2",
      "path": "/var/lib/jenkins/workspace/DWAPPS/pypi-upload/static/fonts/alegreya-sans-latin-700italic.woff2",
      "publicPath": "/static/fonts/alegreya-sans-latin-700italic.woff2"
    },
    "fonts/alegreya-sans-latin-800.woff": {
      "name": "fonts/alegreya-sans-latin-800.woff",
      "path": "/var/lib/jenkins/workspace/DWAPPS/pypi-upload/static/fonts/alegreya-sans-latin-800.woff",
      "publicPath": "/static/fonts/alegreya-sans-latin-800.woff"
    },
    "fonts/alegreya-sans-latin-800.woff2": {
      "name": "fonts/alegreya-sans-latin-800.woff2",
      "path": "/var/lib/jenkins/workspace/DWAPPS/pypi-upload/static/fonts/alegreya-sans-latin-800.woff2",
      "publicPath": "/static/fonts/alegreya-sans-latin-800.woff2"
    },
    "fonts/alegreya-sans-latin-800italic.woff": {
      "name": "fonts/alegreya-sans-latin-800italic.woff",
      "path": "/var/lib/jenkins/workspace/DWAPPS/pypi-upload/static/fonts/alegreya-sans-latin-800italic.woff",
      "publicPath": "/static/fonts/alegreya-sans-latin-800italic.woff"
    },
    "fonts/alegreya-sans-latin-800italic.woff2": {
      "name": "fonts/alegreya-sans-latin-800italic.woff2",
      "path": "/var/lib/jenkins/workspace/DWAPPS/pypi-upload/static/fonts/alegreya-sans-latin-800italic.woff2",
      "publicPath": "/static/fonts/alegreya-sans-latin-800italic.woff2"
    },
    "fonts/alegreya-sans-latin-900.woff": {
      "name": "fonts/alegreya-sans-latin-900.woff",
      "path": "/var/lib/jenkins/workspace/DWAPPS/pypi-upload/static/fonts/alegreya-sans-latin-900.woff",
      "publicPath": "/static/fonts/alegreya-sans-latin-900.woff"
    },
    "fonts/alegreya-sans-latin-900.woff2": {
      "name": "fonts/alegreya-sans-latin-900.woff2",
      "path": "/var/lib/jenkins/workspace/DWAPPS/pypi-upload/static/fonts/alegreya-sans-latin-900.woff2",
      "publicPath": "/static/fonts/alegreya-sans-latin-900.woff2"
    },
    "fonts/alegreya-sans-latin-900italic.woff": {
      "name": "fonts/alegreya-sans-latin-900italic.woff",
      "path": "/var/lib/jenkins/workspace/DWAPPS/pypi-upload/static/fonts/alegreya-sans-latin-900italic.woff",
      "publicPath": "/static/fonts/alegreya-sans-latin-900italic.woff"
    },
    "fonts/alegreya-sans-latin-900italic.woff2": {
      "name": "fonts/alegreya-sans-latin-900italic.woff2",
      "path": "/var/lib/jenkins/workspace/DWAPPS/pypi-upload/static/fonts/alegreya-sans-latin-900italic.woff2",
      "publicPath": "/static/fonts/alegreya-sans-latin-900italic.woff2"
    },
    "fonts/materialdesignicons-webfont.eot": {
      "name": "fonts/materialdesignicons-webfont.eot",
      "path": "/var/lib/jenkins/workspace/DWAPPS/pypi-upload/static/fonts/materialdesignicons-webfont.eot",
      "publicPath": "/static/fonts/materialdesignicons-webfont.eot"
    },
    "fonts/materialdesignicons-webfont.eot?v=7.0.96": {
      "name": "fonts/materialdesignicons-webfont.eot?v=7.0.96",
      "path": "/var/lib/jenkins/workspace/DWAPPS/pypi-upload/static/fonts/materialdesignicons-webfont.eot",
      "publicPath": "/static/fonts/materialdesignicons-webfont.eot?v=7.0.96"
    },
    "fonts/materialdesignicons-webfont.ttf?v=7.0.96": {
      "name": "fonts/materialdesignicons-webfont.ttf?v=7.0.96",
      "path": "/var/lib/jenkins/workspace/DWAPPS/pypi-upload/static/fonts/materialdesignicons-webfont.ttf",
      "publicPath": "/static/fonts/materialdesignicons-webfont.ttf?v=7.0.96"
    },
    "fonts/materialdesignicons-webfont.woff?v=7.0.96": {
      "name": "fonts/materialdesignicons-webfont.woff?v=7.0.96",
      "path": "/var/lib/jenkins/workspace/DWAPPS/pypi-upload/static/fonts/materialdesignicons-webfont.woff",
      "publicPath": "/static/fonts/materialdesignicons-webfont.woff?v=7.0.96"
    },
    "fonts/materialdesignicons-webfont.woff2?v=7.0.96": {
      "name": "fonts/materialdesignicons-webfont.woff2?v=7.0.96",
      "path": "/var/lib/jenkins/workspace/DWAPPS/pypi-upload/static/fonts/materialdesignicons-webfont.woff2",
      "publicPath": "/static/fonts/materialdesignicons-webfont.woff2?v=7.0.96"
    },
    "fonts/MathJax_AMS-Regular.woff": {
      "name": "fonts/MathJax_AMS-Regular.woff",
      "path": "/var/lib/jenkins/workspace/DWAPPS/pypi-upload/static/fonts/MathJax_AMS-Regular.woff",
      "publicPath": "/static/fonts/MathJax_AMS-Regular.woff"
    },
    "fonts/MathJax_Calligraphic-Bold.woff": {
      "name": "fonts/MathJax_Calligraphic-Bold.woff",
      "path": "/var/lib/jenkins/workspace/DWAPPS/pypi-upload/static/fonts/MathJax_Calligraphic-Bold.woff",
      "publicPath": "/static/fonts/MathJax_Calligraphic-Bold.woff"
    },
    "fonts/MathJax_Calligraphic-Regular.woff": {
      "name": "fonts/MathJax_Calligraphic-Regular.woff",
      "path": "/var/lib/jenkins/workspace/DWAPPS/pypi-upload/static/fonts/MathJax_Calligraphic-Regular.woff",
      "publicPath": "/static/fonts/MathJax_Calligraphic-Regular.woff"
    },
    "fonts/MathJax_Fraktur-Bold.woff": {
      "name": "fonts/MathJax_Fraktur-Bold.woff",
      "path": "/var/lib/jenkins/workspace/DWAPPS/pypi-upload/static/fonts/MathJax_Fraktur-Bold.woff",
      "publicPath": "/static/fonts/MathJax_Fraktur-Bold.woff"
    },
    "fonts/MathJax_Fraktur-Regular.woff": {
      "name": "fonts/MathJax_Fraktur-Regular.woff",
      "path": "/var/lib/jenkins/workspace/DWAPPS/pypi-upload/static/fonts/MathJax_Fraktur-Regular.woff",
      "publicPath": "/static/fonts/MathJax_Fraktur-Regular.woff"
    },
    "fonts/MathJax_Main-Bold.woff": {
      "name": "fonts/MathJax_Main-Bold.woff",
      "path": "/var/lib/jenkins/workspace/DWAPPS/pypi-upload/static/fonts/MathJax_Main-Bold.woff",
      "publicPath": "/static/fonts/MathJax_Main-Bold.woff"
    },
    "fonts/MathJax_Main-Italic.woff": {
      "name": "fonts/MathJax_Main-Italic.woff",
      "path": "/var/lib/jenkins/workspace/DWAPPS/pypi-upload/static/fonts/MathJax_Main-Italic.woff",
      "publicPath": "/static/fonts/MathJax_Main-Italic.woff"
    },
    "fonts/MathJax_Main-Regular.woff": {
      "name": "fonts/MathJax_Main-Regular.woff",
      "path": "/var/lib/jenkins/workspace/DWAPPS/pypi-upload/static/fonts/MathJax_Main-Regular.woff",
      "publicPath": "/static/fonts/MathJax_Main-Regular.woff"
    },
    "fonts/MathJax_Math-BoldItalic.woff": {
      "name": "fonts/MathJax_Math-BoldItalic.woff",
      "path": "/var/lib/jenkins/workspace/DWAPPS/pypi-upload/static/fonts/MathJax_Math-BoldItalic.woff",
      "publicPath": "/static/fonts/MathJax_Math-BoldItalic.woff"
    },
    "fonts/MathJax_Math-Italic.woff": {
      "name": "fonts/MathJax_Math-Italic.woff",
      "path": "/var/lib/jenkins/workspace/DWAPPS/pypi-upload/static/fonts/MathJax_Math-Italic.woff",
      "publicPath": "/static/fonts/MathJax_Math-Italic.woff"
    },
    "fonts/MathJax_Math-Regular.woff": {
      "name": "fonts/MathJax_Math-Regular.woff",
      "path": "/var/lib/jenkins/workspace/DWAPPS/pypi-upload/static/fonts/MathJax_Math-Regular.woff",
      "publicPath": "/static/fonts/MathJax_Math-Regular.woff"
    },
    "fonts/MathJax_SansSerif-Bold.woff": {
      "name": "fonts/MathJax_SansSerif-Bold.woff",
      "path": "/var/lib/jenkins/workspace/DWAPPS/pypi-upload/static/fonts/MathJax_SansSerif-Bold.woff",
      "publicPath": "/static/fonts/MathJax_SansSerif-Bold.woff"
    },
    "fonts/MathJax_SansSerif-Italic.woff": {
      "name": "fonts/MathJax_SansSerif-Italic.woff",
      "path": "/var/lib/jenkins/workspace/DWAPPS/pypi-upload/static/fonts/MathJax_SansSerif-Italic.woff",
      "publicPath": "/static/fonts/MathJax_SansSerif-Italic.woff"
    },
    "fonts/MathJax_SansSerif-Regular.woff": {
      "name": "fonts/MathJax_SansSerif-Regular.woff",
      "path": "/var/lib/jenkins/workspace/DWAPPS/pypi-upload/static/fonts/MathJax_SansSerif-Regular.woff",
      "publicPath": "/static/fonts/MathJax_SansSerif-Regular.woff"
    },
    "fonts/MathJax_Script-Regular.woff": {
      "name": "fonts/MathJax_Script-Regular.woff",
      "path": "/var/lib/jenkins/workspace/DWAPPS/pypi-upload/static/fonts/MathJax_Script-Regular.woff",
      "publicPath": "/static/fonts/MathJax_Script-Regular.woff"
    },
    "fonts/MathJax_Size1-Regular.woff": {
      "name": "fonts/MathJax_Size1-Regular.woff",
      "path": "/var/lib/jenkins/workspace/DWAPPS/pypi-upload/static/fonts/MathJax_Size1-Regular.woff",
      "publicPath": "/static/fonts/MathJax_Size1-Regular.woff"
    },
    "fonts/MathJax_Size2-Regular.woff": {
      "name": "fonts/MathJax_Size2-Regular.woff",
      "path": "/var/lib/jenkins/workspace/DWAPPS/pypi-upload/static/fonts/MathJax_Size2-Regular.woff",
      "publicPath": "/static/fonts/MathJax_Size2-Regular.woff"
    },
    "fonts/MathJax_Size3-Regular.woff": {
      "name": "fonts/MathJax_Size3-Regular.woff",
      "path": "/var/lib/jenkins/workspace/DWAPPS/pypi-upload/static/fonts/MathJax_Size3-Regular.woff",
      "publicPath": "/static/fonts/MathJax_Size3-Regular.woff"
    },
    "fonts/MathJax_Size4-Regular.woff": {
      "name": "fonts/MathJax_Size4-Regular.woff",
      "path": "/var/lib/jenkins/workspace/DWAPPS/pypi-upload/static/fonts/MathJax_Size4-Regular.woff",
      "publicPath": "/static/fonts/MathJax_Size4-Regular.woff"
    },
    "fonts/MathJax_Typewriter-Regular.woff": {
      "name": "fonts/MathJax_Typewriter-Regular.woff",
      "path": "/var/lib/jenkins/workspace/DWAPPS/pypi-upload/static/fonts/MathJax_Typewriter-Regular.woff",
      "publicPath": "/static/fonts/MathJax_Typewriter-Regular.woff"
    },
    "fonts/MathJax_Vector-Bold.woff": {
      "name": "fonts/MathJax_Vector-Bold.woff",
      "path": "/var/lib/jenkins/workspace/DWAPPS/pypi-upload/static/fonts/MathJax_Vector-Bold.woff",
      "publicPath": "/static/fonts/MathJax_Vector-Bold.woff"
    },
    "fonts/MathJax_Vector-Regular.woff": {
      "name": "fonts/MathJax_Vector-Regular.woff",
      "path": "/var/lib/jenkins/workspace/DWAPPS/pypi-upload/static/fonts/MathJax_Vector-Regular.woff",
      "publicPath": "/static/fonts/MathJax_Vector-Regular.woff"
    },
    "fonts/MathJax_Zero.woff": {
      "name": "fonts/MathJax_Zero.woff",
      "path": "/var/lib/jenkins/workspace/DWAPPS/pypi-upload/static/fonts/MathJax_Zero.woff",
      "publicPath": "/static/fonts/MathJax_Zero.woff"
    },
    "img/thirdParty/chosen-sprite.png": {
      "name": "img/thirdParty/chosen-sprite.png",
      "path": "/var/lib/jenkins/workspace/DWAPPS/pypi-upload/static/img/thirdParty/chosen-sprite.png",
      "publicPath": "/static/img/thirdParty/chosen-sprite.png"
    },
    "img/thirdParty/chosen-sprite@2x.png": {
      "name": "img/thirdParty/chosen-sprite@2x.png",
      "path": "/var/lib/jenkins/workspace/DWAPPS/pypi-upload/static/img/thirdParty/chosen-sprite@2x.png",
      "publicPath": "/static/img/thirdParty/chosen-sprite@2x.png"
    },
    "js/add_forge_now.6e82eb70e389b653cd95.js": {
      "name": "js/add_forge_now.6e82eb70e389b653cd95.js",
      "path": "/var/lib/jenkins/workspace/DWAPPS/pypi-upload/static/js/add_forge_now.6e82eb70e389b653cd95.js",
      "publicPath": "/static/js/add_forge_now.6e82eb70e389b653cd95.js"
    },
    "js/add_forge_now.6e82eb70e389b653cd95.js.LICENSE.txt": {
      "name": "js/add_forge_now.6e82eb70e389b653cd95.js.LICENSE.txt",
      "path": "/var/lib/jenkins/workspace/DWAPPS/pypi-upload/static/js/add_forge_now.6e82eb70e389b653cd95.js.LICENSE.txt",
      "publicPath": "/static/js/add_forge_now.6e82eb70e389b653cd95.js.LICENSE.txt"
    },
    "js/add_forge_now.6e82eb70e389b653cd95.js.map": {
      "name": "js/add_forge_now.6e82eb70e389b653cd95.js.map",
      "path": "/var/lib/jenkins/workspace/DWAPPS/pypi-upload/static/js/add_forge_now.6e82eb70e389b653cd95.js.map",
      "publicPath": "/static/js/add_forge_now.6e82eb70e389b653cd95.js.map"
    },
    "js/archive_coverage.4bf1d7409bfff73fb931.js": {
      "name": "js/archive_coverage.4bf1d7409bfff73fb931.js",
      "path": "/var/lib/jenkins/workspace/DWAPPS/pypi-upload/static/js/archive_coverage.4bf1d7409bfff73fb931.js",
      "publicPath": "/static/js/archive_coverage.4bf1d7409bfff73fb931.js"
    },
    "js/archive_coverage.4bf1d7409bfff73fb931.js.map": {
      "name": "js/archive_coverage.4bf1d7409bfff73fb931.js.map",
      "path": "/var/lib/jenkins/workspace/DWAPPS/pypi-upload/static/js/archive_coverage.4bf1d7409bfff73fb931.js.map",
      "publicPath": "/static/js/archive_coverage.4bf1d7409bfff73fb931.js.map"
    },
    "js/auth.3fd583150a2cb73b1786.js": {
      "name": "js/auth.3fd583150a2cb73b1786.js",
      "path": "/var/lib/jenkins/workspace/DWAPPS/pypi-upload/static/js/auth.3fd583150a2cb73b1786.js",
      "publicPath": "/static/js/auth.3fd583150a2cb73b1786.js"
    },
    "js/auth.3fd583150a2cb73b1786.js.LICENSE.txt": {
      "name": "js/auth.3fd583150a2cb73b1786.js.LICENSE.txt",
      "path": "/var/lib/jenkins/workspace/DWAPPS/pypi-upload/static/js/auth.3fd583150a2cb73b1786.js.LICENSE.txt",
      "publicPath": "/static/js/auth.3fd583150a2cb73b1786.js.LICENSE.txt"
    },
    "js/auth.3fd583150a2cb73b1786.js.map": {
      "name": "js/auth.3fd583150a2cb73b1786.js.map",
      "path": "/var/lib/jenkins/workspace/DWAPPS/pypi-upload/static/js/auth.3fd583150a2cb73b1786.js.map",
      "publicPath": "/static/js/auth.3fd583150a2cb73b1786.js.map"
    },
    "js/browse.6fc94389641d9b78079b.js": {
      "name": "js/browse.6fc94389641d9b78079b.js",
      "path": "/var/lib/jenkins/workspace/DWAPPS/pypi-upload/static/js/browse.6fc94389641d9b78079b.js",
      "publicPath": "/static/js/browse.6fc94389641d9b78079b.js"
    },
    "js/browse.6fc94389641d9b78079b.js.LICENSE.txt": {
      "name": "js/browse.6fc94389641d9b78079b.js.LICENSE.txt",
      "path": "/var/lib/jenkins/workspace/DWAPPS/pypi-upload/static/js/browse.6fc94389641d9b78079b.js.LICENSE.txt",
      "publicPath": "/static/js/browse.6fc94389641d9b78079b.js.LICENSE.txt"
    },
    "js/browse.6fc94389641d9b78079b.js.map": {
      "name": "js/browse.6fc94389641d9b78079b.js.map",
      "path": "/var/lib/jenkins/workspace/DWAPPS/pypi-upload/static/js/browse.6fc94389641d9b78079b.js.map",
      "publicPath": "/static/js/browse.6fc94389641d9b78079b.js.map"
    },
    "js/d3.9a0d48ae00854a5a1b5d.js": {
      "name": "js/d3.9a0d48ae00854a5a1b5d.js",
      "path": "/var/lib/jenkins/workspace/DWAPPS/pypi-upload/static/js/d3.9a0d48ae00854a5a1b5d.js",
      "publicPath": "/static/js/d3.9a0d48ae00854a5a1b5d.js"
    },
    "js/d3.9a0d48ae00854a5a1b5d.js.map": {
      "name": "js/d3.9a0d48ae00854a5a1b5d.js.map",
      "path": "/var/lib/jenkins/workspace/DWAPPS/pypi-upload/static/js/d3.9a0d48ae00854a5a1b5d.js.map",
      "publicPath": "/static/js/d3.9a0d48ae00854a5a1b5d.js.map"
    },
    "js/deposit.2cc3b7da9416e8f9c670.js": {
      "name": "js/deposit.2cc3b7da9416e8f9c670.js",
      "path": "/var/lib/jenkins/workspace/DWAPPS/pypi-upload/static/js/deposit.2cc3b7da9416e8f9c670.js",
      "publicPath": "/static/js/deposit.2cc3b7da9416e8f9c670.js"
    },
    "js/deposit.2cc3b7da9416e8f9c670.js.LICENSE.txt": {
      "name": "js/deposit.2cc3b7da9416e8f9c670.js.LICENSE.txt",
      "path": "/var/lib/jenkins/workspace/DWAPPS/pypi-upload/static/js/deposit.2cc3b7da9416e8f9c670.js.LICENSE.txt",
      "publicPath": "/static/js/deposit.2cc3b7da9416e8f9c670.js.LICENSE.txt"
    },
    "js/deposit.2cc3b7da9416e8f9c670.js.map": {
      "name": "js/deposit.2cc3b7da9416e8f9c670.js.map",
      "path": "/var/lib/jenkins/workspace/DWAPPS/pypi-upload/static/js/deposit.2cc3b7da9416e8f9c670.js.map",
      "publicPath": "/static/js/deposit.2cc3b7da9416e8f9c670.js.map"
    },
    "js/guided_tour.b8ac7056cfac5070622c.js": {
      "name": "js/guided_tour.b8ac7056cfac5070622c.js",
      "path": "/var/lib/jenkins/workspace/DWAPPS/pypi-upload/static/js/guided_tour.b8ac7056cfac5070622c.js",
      "publicPath": "/static/js/guided_tour.b8ac7056cfac5070622c.js"
    },
    "js/guided_tour.b8ac7056cfac5070622c.js.LICENSE.txt": {
      "name": "js/guided_tour.b8ac7056cfac5070622c.js.LICENSE.txt",
      "path": "/var/lib/jenkins/workspace/DWAPPS/pypi-upload/static/js/guided_tour.b8ac7056cfac5070622c.js.LICENSE.txt",
      "publicPath": "/static/js/guided_tour.b8ac7056cfac5070622c.js.LICENSE.txt"
    },
    "js/guided_tour.b8ac7056cfac5070622c.js.map": {
      "name": "js/guided_tour.b8ac7056cfac5070622c.js.map",
      "path": "/var/lib/jenkins/workspace/DWAPPS/pypi-upload/static/js/guided_tour.b8ac7056cfac5070622c.js.map",
      "publicPath": "/static/js/guided_tour.b8ac7056cfac5070622c.js.map"
    },
    "js/highlightjs.ea9ab9de27a6e276ec47.js": {
      "name": "js/highlightjs.ea9ab9de27a6e276ec47.js",
      "path": "/var/lib/jenkins/workspace/DWAPPS/pypi-upload/static/js/highlightjs.ea9ab9de27a6e276ec47.js",
      "publicPath": "/static/js/highlightjs.ea9ab9de27a6e276ec47.js"
    },
    "js/highlightjs.ea9ab9de27a6e276ec47.js.LICENSE.txt": {
      "name": "js/highlightjs.ea9ab9de27a6e276ec47.js.LICENSE.txt",
      "path": "/var/lib/jenkins/workspace/DWAPPS/pypi-upload/static/js/highlightjs.ea9ab9de27a6e276ec47.js.LICENSE.txt",
      "publicPath": "/static/js/highlightjs.ea9ab9de27a6e276ec47.js.LICENSE.txt"
    },
    "js/highlightjs.ea9ab9de27a6e276ec47.js.map": {
      "name": "js/highlightjs.ea9ab9de27a6e276ec47.js.map",
      "path": "/var/lib/jenkins/workspace/DWAPPS/pypi-upload/static/js/highlightjs.ea9ab9de27a6e276ec47.js.map",
      "publicPath": "/static/js/highlightjs.ea9ab9de27a6e276ec47.js.map"
    },
    "js/mailmap.955cdd4b0086c3de5378.js": {
      "name": "js/mailmap.955cdd4b0086c3de5378.js",
      "path": "/var/lib/jenkins/workspace/DWAPPS/pypi-upload/static/js/mailmap.955cdd4b0086c3de5378.js",
      "publicPath": "/static/js/mailmap.955cdd4b0086c3de5378.js"
    },
    "js/mailmap.955cdd4b0086c3de5378.js.LICENSE.txt": {
      "name": "js/mailmap.955cdd4b0086c3de5378.js.LICENSE.txt",
      "path": "/var/lib/jenkins/workspace/DWAPPS/pypi-upload/static/js/mailmap.955cdd4b0086c3de5378.js.LICENSE.txt",
      "publicPath": "/static/js/mailmap.955cdd4b0086c3de5378.js.LICENSE.txt"
    },
    "js/mailmap.955cdd4b0086c3de5378.js.map": {
      "name": "js/mailmap.955cdd4b0086c3de5378.js.map",
      "path": "/var/lib/jenkins/workspace/DWAPPS/pypi-upload/static/js/mailmap.955cdd4b0086c3de5378.js.map",
      "publicPath": "/static/js/mailmap.955cdd4b0086c3de5378.js.map"
    },
    "js/mathjax.8052aaae7f18c4bbf50f.js": {
      "name": "js/mathjax.8052aaae7f18c4bbf50f.js",
      "path": "/var/lib/jenkins/workspace/DWAPPS/pypi-upload/static/js/mathjax.8052aaae7f18c4bbf50f.js",
      "publicPath": "/static/js/mathjax.8052aaae7f18c4bbf50f.js"
    },
    "js/mathjax.8052aaae7f18c4bbf50f.js.map": {
      "name": "js/mathjax.8052aaae7f18c4bbf50f.js.map",
      "path": "/var/lib/jenkins/workspace/DWAPPS/pypi-upload/static/js/mathjax.8052aaae7f18c4bbf50f.js.map",
      "publicPath": "/static/js/mathjax.8052aaae7f18c4bbf50f.js.map"
    },
    "js/org.9adc9a39a210c2fb4be0.js": {
      "name": "js/org.9adc9a39a210c2fb4be0.js",
      "path": "/var/lib/jenkins/workspace/DWAPPS/pypi-upload/static/js/org.9adc9a39a210c2fb4be0.js",
      "publicPath": "/static/js/org.9adc9a39a210c2fb4be0.js"
    },
    "js/org.9adc9a39a210c2fb4be0.js.map": {
      "name": "js/org.9adc9a39a210c2fb4be0.js.map",
      "path": "/var/lib/jenkins/workspace/DWAPPS/pypi-upload/static/js/org.9adc9a39a210c2fb4be0.js.map",
      "publicPath": "/static/js/org.9adc9a39a210c2fb4be0.js.map"
    },
    "js/origin_visits.8dd91a10feecb3e022c4.js": {
      "name": "js/origin_visits.8dd91a10feecb3e022c4.js",
      "path": "/var/lib/jenkins/workspace/DWAPPS/pypi-upload/static/js/origin_visits.8dd91a10feecb3e022c4.js",
      "publicPath": "/static/js/origin_visits.8dd91a10feecb3e022c4.js"
    },
    "js/origin_visits.8dd91a10feecb3e022c4.js.map": {
      "name": "js/origin_visits.8dd91a10feecb3e022c4.js.map",
      "path": "/var/lib/jenkins/workspace/DWAPPS/pypi-upload/static/js/origin_visits.8dd91a10feecb3e022c4.js.map",
      "publicPath": "/static/js/origin_visits.8dd91a10feecb3e022c4.js.map"
    },
    "js/pdf.worker.min.js": {
      "name": "js/pdf.worker.min.js",
      "path": "/var/lib/jenkins/workspace/DWAPPS/pypi-upload/static/js/pdf.worker.min.js",
      "publicPath": "/static/js/pdf.worker.min.js"
    },
    "js/pdf.worker.min.js.LICENSE.txt": {
      "name": "js/pdf.worker.min.js.LICENSE.txt",
      "path": "/var/lib/jenkins/workspace/DWAPPS/pypi-upload/static/js/pdf.worker.min.js.LICENSE.txt",
      "publicPath": "/static/js/pdf.worker.min.js.LICENSE.txt"
    },
    "js/pdfjs.9e0f3974fef1477cda42.js": {
      "name": "js/pdfjs.9e0f3974fef1477cda42.js",
      "path": "/var/lib/jenkins/workspace/DWAPPS/pypi-upload/static/js/pdfjs.9e0f3974fef1477cda42.js",
      "publicPath": "/static/js/pdfjs.9e0f3974fef1477cda42.js"
    },
    "js/pdfjs.9e0f3974fef1477cda42.js.map": {
      "name": "js/pdfjs.9e0f3974fef1477cda42.js.map",
      "path": "/var/lib/jenkins/workspace/DWAPPS/pypi-upload/static/js/pdfjs.9e0f3974fef1477cda42.js.map",
      "publicPath": "/static/js/pdfjs.9e0f3974fef1477cda42.js.map"
    },
    "js/revision.f04f914840ac12f33c46.js": {
      "name": "js/revision.f04f914840ac12f33c46.js",
      "path": "/var/lib/jenkins/workspace/DWAPPS/pypi-upload/static/js/revision.f04f914840ac12f33c46.js",
      "publicPath": "/static/js/revision.f04f914840ac12f33c46.js"
    },
    "js/revision.f04f914840ac12f33c46.js.LICENSE.txt": {
      "name": "js/revision.f04f914840ac12f33c46.js.LICENSE.txt",
      "path": "/var/lib/jenkins/workspace/DWAPPS/pypi-upload/static/js/revision.f04f914840ac12f33c46.js.LICENSE.txt",
      "publicPath": "/static/js/revision.f04f914840ac12f33c46.js.LICENSE.txt"
    },
    "js/revision.f04f914840ac12f33c46.js.map": {
      "name": "js/revision.f04f914840ac12f33c46.js.map",
      "path": "/var/lib/jenkins/workspace/DWAPPS/pypi-upload/static/js/revision.f04f914840ac12f33c46.js.map",
      "publicPath": "/static/js/revision.f04f914840ac12f33c46.js.map"
    },
    "js/save_code_now.a0c4f24d0b4d3a36b12a.js": {
      "name": "js/save_code_now.a0c4f24d0b4d3a36b12a.js",
      "path": "/var/lib/jenkins/workspace/DWAPPS/pypi-upload/static/js/save_code_now.a0c4f24d0b4d3a36b12a.js",
      "publicPath": "/static/js/save_code_now.a0c4f24d0b4d3a36b12a.js"
    },
    "js/save_code_now.a0c4f24d0b4d3a36b12a.js.LICENSE.txt": {
      "name": "js/save_code_now.a0c4f24d0b4d3a36b12a.js.LICENSE.txt",
      "path": "/var/lib/jenkins/workspace/DWAPPS/pypi-upload/static/js/save_code_now.a0c4f24d0b4d3a36b12a.js.LICENSE.txt",
      "publicPath": "/static/js/save_code_now.a0c4f24d0b4d3a36b12a.js.LICENSE.txt"
    },
    "js/save_code_now.a0c4f24d0b4d3a36b12a.js.map": {
      "name": "js/save_code_now.a0c4f24d0b4d3a36b12a.js.map",
      "path": "/var/lib/jenkins/workspace/DWAPPS/pypi-upload/static/js/save_code_now.a0c4f24d0b4d3a36b12a.js.map",
      "publicPath": "/static/js/save_code_now.a0c4f24d0b4d3a36b12a.js.map"
    },
    "js/showdown.b448e42a34c43d6a7de5.js": {
      "name": "js/showdown.b448e42a34c43d6a7de5.js",
      "path": "/var/lib/jenkins/workspace/DWAPPS/pypi-upload/static/js/showdown.b448e42a34c43d6a7de5.js",
      "publicPath": "/static/js/showdown.b448e42a34c43d6a7de5.js"
    },
    "js/showdown.b448e42a34c43d6a7de5.js.LICENSE.txt": {
      "name": "js/showdown.b448e42a34c43d6a7de5.js.LICENSE.txt",
      "path": "/var/lib/jenkins/workspace/DWAPPS/pypi-upload/static/js/showdown.b448e42a34c43d6a7de5.js.LICENSE.txt",
      "publicPath": "/static/js/showdown.b448e42a34c43d6a7de5.js.LICENSE.txt"
    },
    "js/showdown.b448e42a34c43d6a7de5.js.map": {
      "name": "js/showdown.b448e42a34c43d6a7de5.js.map",
      "path": "/var/lib/jenkins/workspace/DWAPPS/pypi-upload/static/js/showdown.b448e42a34c43d6a7de5.js.map",
      "publicPath": "/static/js/showdown.b448e42a34c43d6a7de5.js.map"
    },
    "js/vault.5125ce73c2eefea7da06.js": {
      "name": "js/vault.5125ce73c2eefea7da06.js",
      "path": "/var/lib/jenkins/workspace/DWAPPS/pypi-upload/static/js/vault.5125ce73c2eefea7da06.js",
      "publicPath": "/static/js/vault.5125ce73c2eefea7da06.js"
    },
    "js/vault.5125ce73c2eefea7da06.js.LICENSE.txt": {
      "name": "js/vault.5125ce73c2eefea7da06.js.LICENSE.txt",
      "path": "/var/lib/jenkins/workspace/DWAPPS/pypi-upload/static/js/vault.5125ce73c2eefea7da06.js.LICENSE.txt",
      "publicPath": "/static/js/vault.5125ce73c2eefea7da06.js.LICENSE.txt"
    },
    "js/vault.5125ce73c2eefea7da06.js.map": {
      "name": "js/vault.5125ce73c2eefea7da06.js.map",
      "path": "/var/lib/jenkins/workspace/DWAPPS/pypi-upload/static/js/vault.5125ce73c2eefea7da06.js.map",
      "publicPath": "/static/js/vault.5125ce73c2eefea7da06.js.map"
    },
    "js/vendors.66bb8218a173e76da5b3.js": {
      "name": "js/vendors.66bb8218a173e76da5b3.js",
      "path": "/var/lib/jenkins/workspace/DWAPPS/pypi-upload/static/js/vendors.66bb8218a173e76da5b3.js",
      "publicPath": "/static/js/vendors.66bb8218a173e76da5b3.js"
    },
    "js/vendors.66bb8218a173e76da5b3.js.LICENSE.txt": {
      "name": "js/vendors.66bb8218a173e76da5b3.js.LICENSE.txt",
      "path": "/var/lib/jenkins/workspace/DWAPPS/pypi-upload/static/js/vendors.66bb8218a173e76da5b3.js.LICENSE.txt",
      "publicPath": "/static/js/vendors.66bb8218a173e76da5b3.js.LICENSE.txt"
    },
    "js/vendors.66bb8218a173e76da5b3.js.map": {
      "name": "js/vendors.66bb8218a173e76da5b3.js.map",
      "path": "/var/lib/jenkins/workspace/DWAPPS/pypi-upload/static/js/vendors.66bb8218a173e76da5b3.js.map",
      "publicPath": "/static/js/vendors.66bb8218a173e76da5b3.js.map"
    },
    "js/webapp.0733a6627b287de8a4ed.js": {
      "name": "js/webapp.0733a6627b287de8a4ed.js",
      "path": "/var/lib/jenkins/workspace/DWAPPS/pypi-upload/static/js/webapp.0733a6627b287de8a4ed.js",
      "publicPath": "/static/js/webapp.0733a6627b287de8a4ed.js"
    },
    "js/webapp.0733a6627b287de8a4ed.js.LICENSE.txt": {
      "name": "js/webapp.0733a6627b287de8a4ed.js.LICENSE.txt",
      "path": "/var/lib/jenkins/workspace/DWAPPS/pypi-upload/static/js/webapp.0733a6627b287de8a4ed.js.LICENSE.txt",
      "publicPath": "/static/js/webapp.0733a6627b287de8a4ed.js.LICENSE.txt"
    },
    "js/webapp.0733a6627b287de8a4ed.js.map": {
      "name": "js/webapp.0733a6627b287de8a4ed.js.map",
      "path": "/var/lib/jenkins/workspace/DWAPPS/pypi-upload/static/js/webapp.0733a6627b287de8a4ed.js.map",
      "publicPath": "/static/js/webapp.0733a6627b287de8a4ed.js.map"
    },
    "robots.txt": {
      "name": "robots.txt",
      "path": "/var/lib/jenkins/workspace/DWAPPS/pypi-upload/static/robots.txt",
      "publicPath": "/static/robots.txt"
    }
  },
  "chunks": {
    "add_forge_now": [
      "css/add_forge_now.4f93c9769bc36a247915.css",
      "js/add_forge_now.6e82eb70e389b653cd95.js"
    ],
    "archive_coverage": [
      "css/archive_coverage.243fd0a38715dd7ff3e5.css",
      "js/archive_coverage.4bf1d7409bfff73fb931.js"
    ],
    "auth": [
      "css/auth.0336a94c2c02b4b2a4f4.css",
      "js/auth.3fd583150a2cb73b1786.js"
    ],
    "browse": [
      "css/browse.3381f65cfada5255789a.css",
      "js/browse.6fc94389641d9b78079b.js"
    ],
    "deposit": [
      "js/deposit.2cc3b7da9416e8f9c670.js"
    ],
    "guided_tour": [
      "css/guided_tour.877fa77fcebc36a05b5c.css",
      "js/guided_tour.b8ac7056cfac5070622c.js"
    ],
    "mailmap": [
      "js/mailmap.955cdd4b0086c3de5378.js"
    ],
    "origin_visits": [
      "css/origin_visits.f74f3ffcbbce22294008.css",
      "js/origin_visits.8dd91a10feecb3e022c4.js"
    ],
    "revision": [
      "css/revision.5ddd36d69e1760bfa29d.css",
      "js/revision.f04f914840ac12f33c46.js"
    ],
    "save_code_now": [
      "js/save_code_now.a0c4f24d0b4d3a36b12a.js"
    ],
    "vault": [
      "css/vault.25fc5883f848b48ffa5b.css",
      "js/vault.5125ce73c2eefea7da06.js"
    ],
    "vendors": [
      "css/vendors.dfce793c06269b88766c.css",
      "js/vendors.66bb8218a173e76da5b3.js"
    ],
    "webapp": [
      "css/webapp.a5ee322795df19e158b7.css",
      "js/webapp.0733a6627b287de8a4ed.js"
    ]
  },
  "publicPath": "/static/"
}